[
    {
        "answer_id": 3460713084,
        "content": "把劳资的蛋蛋还给我",
        "voteup_count": 56,
        "updated_time": "2024-04-10 10:46:52",
        "question_id": 650233433,
        "user_id": "04791522a522818f9bb42e92c6c99453"
    },
    {
        "answer_id": 3479756646,
        "content": "人情往来，不就是罐来罐去嘛",
        "voteup_count": 30,
        "updated_time": "2024-04-26 20:15:51",
        "question_id": 650233433,
        "user_id": "139234974853b9ca722e565d27f0e89c"
    },
    {
        "answer_id": 3480621068,
        "content": "我的猫猫可能没有签名，也没有动态，因为他是一个成熟稳重的猫猫，毕竟他在家，也是对我爱答不理的。如果非要让他写一个签名，那一定只有两个高冷的字：“罐罐”",
        "voteup_count": 42,
        "updated_time": "2024-04-27 18:10:37",
        "question_id": 650233433,
        "user_id": "6416065e2bcb4bee52f9e9cc913bc6f3"
    },
    {
        "answer_id": 3482212775,
        "content": "我tm超屌！",
        "voteup_count": 2,
        "updated_time": "2024-04-29 08:38:21",
        "question_id": 650233433,
        "user_id": "12d77eb39ca9e2851a014504f31aebd8"
    },
    {
        "answer_id": 3478604874,
        "content": "根据我对我家之前养过的那狸花猫的了解，她要是有微信了，她的签名会是 ”放荡不羁爱自由“”。她那个心，真是是野啊，老是不着家，三天两头往外面跑，经常在外面浪，感觉就像是个江湖猫，刚开始也有点担心她，后来也就慢慢习惯啦",
        "voteup_count": 11,
        "updated_time": "2024-04-25 20:49:36",
        "question_id": 650233433,
        "user_id": "126145dc82f1e459c90c4ebee2e07f4f"
    },
    {
        "answer_id": 3481921937,
        "content": "猫  : 一天24小时，你有10小时在打工和打工的路上，就挣了那两个糟钱？？",
        "voteup_count": 10,
        "updated_time": "2024-04-28 21:42:28",
        "question_id": 650233433,
        "user_id": "728047965c7ebd6ff5a767a30f261bb8"
    },
    {
        "answer_id": 3481729749,
        "content": "一天到晚也不知道在拍什么！！！！没完没了？",
        "voteup_count": 3,
        "updated_time": "2024-04-28 19:57:50",
        "question_id": 650233433,
        "user_id": "c95f9098876b8c9eb4e89dccbb60baee"
    },
    {
        "answer_id": 3479238667,
        "content": "我是妈妈最爱的崽儿。对，妥妥的妈宝喵～",
        "voteup_count": 3,
        "updated_time": "2024-04-26 12:14:10",
        "question_id": 650233433,
        "user_id": "504319cd086610fb66c1939b6139c86b"
    },
    {
        "answer_id": 3481761789,
        "content": "摩羯座男生，2岁，每天都很烦躁，平时不爱说话，爱摆臭脸，一言不合就哼哼唧唧。个性签名：哼",
        "voteup_count": 8,
        "updated_time": "2024-04-28 18:22:28",
        "question_id": 650233433,
        "user_id": "01fd2857d015bc4b22b7fb508530bec7"
    },
    {
        "answer_id": 3478988094,
        "content": "糊糊：妈妈妈妈妈妈妈妈！我和我妈妈天下第一最最好！（哎嘿是我，它是妈宝男，我坐哪里都要挤我身上）",
        "voteup_count": 11,
        "updated_time": "2024-04-26 09:10:16",
        "question_id": 650233433,
        "user_id": "d631bcedf5beb7546efd1e030a56f5f4"
    },
    {
        "answer_id": 3478996906,
        "content": "巷子里的猫，很自由却没有归宿。围墙里的狗，有归宿终身都得低头。而我，有自由又有归宿，喵喵喵～ps:大冬天捡到的流浪猫，天一暖和就整天往外跑，到饭点知道回来，特别聪明的一只小猫",
        "voteup_count": 7,
        "updated_time": "2024-04-26 09:16:47",
        "question_id": 650233433,
        "user_id": "4e715cc1cb140eadae00ecaaa988ab8e"
    },
    {
        "answer_id": 3482709932,
        "content": "小楼昨夜又东风，故国不堪回首月明中。雕栏玉砌应犹在，只是朱颜改。叨唻咪应该是个忧郁的文艺小猫吧，毕竟它“柔弱不能自理”。单身妈妈带娃记，他喵的还是六个。瞅我干哈！我脸上有吃的啊！主人杯子里的水就是好喝！",
        "voteup_count": 3,
        "updated_time": "2024-04-29 15:43:05",
        "question_id": 650233433,
        "user_id": "eff2e4f2b90d0d0d900bae475f7f1f03"
    },
    {
        "answer_id": 3481675430,
        "content": "大概就是：吾有一主，经常手欠！剪我指甲，薅我猫毛！",
        "voteup_count": 7,
        "updated_time": "2024-04-28 16:57:32",
        "question_id": 650233433,
        "user_id": "299a44b0a016aa37ca30ac4c19e94483"
    },
    {
        "answer_id": 3478084553,
        "content": "我的猫猫估计会一天发很多次朋友圈。凌晨四点醒了发一条，我的仆人还在睡觉，真是不靠谱，巡逻这个事还是交给我吧。七点我醒了，他又发一条，我的仆人终于醒了要去给我捕猎去了。晚上八点我回家时再发一条。仆人回来了，我有吃的了。因为下班我会给他加餐的，猫条，猫罐头或者冻干。这应该是他一天中最开心的时候了。",
        "voteup_count": 14,
        "updated_time": "2024-04-25 12:38:25",
        "question_id": 650233433,
        "user_id": "8503973a804d8ec24b25a57f21470f9c"
    },
    {
        "answer_id": 3482593132,
        "content": "我猜应该是写：用傲娇丈量生活，用智慧洞察世界；生活不止眼前的罐罐，还有远方被我征服的沙发；眼里藏着宇宙的星辰大海，脚步踏着征服世界的骄傲诗篇，尾巴勾勒出幸福的螺旋……那就是我哦，你的小可爱……嗯……好像有点多，但似乎真的有这么多",
        "voteup_count": 3,
        "updated_time": "2024-04-29 14:00:09",
        "question_id": 650233433,
        "user_id": "ebb54f53fa64139c26e67d0e9669cbb2"
    },
    {
        "answer_id": 3479501227,
        "content": "我的猫可能会写   妈妈贴贴",
        "voteup_count": 1,
        "updated_time": "2024-04-26 15:59:06",
        "question_id": 650233433,
        "user_id": "9d36bb12faa83148fceba53619174bcd"
    },
    {
        "answer_id": 3481237217,
        "content": "“已读，不回”",
        "voteup_count": 7,
        "updated_time": "2024-04-28 10:41:20",
        "question_id": 650233433,
        "user_id": "0d46dd86ff80f171521b14b505edb4eb"
    },
    {
        "answer_id": 3482565776,
        "content": "都给老子死哈哈哈哈哈哈哈哈不好意思搞错了 是这个",
        "voteup_count": 1,
        "updated_time": "2024-04-29 13:33:08",
        "question_id": 650233433,
        "user_id": "5cb2d9d7e2cb41cb58f4e45d697540a6"
    },
    {
        "answer_id": 3481533733,
        "content": "半天没陪我玩了，我该去咬一口提醒提醒了。。。",
        "voteup_count": 2,
        "updated_time": "2024-04-28 14:56:44",
        "question_id": 650233433,
        "user_id": "0e38a687a63ff39417e50412ac638c6f"
    },
    {
        "answer_id": 3471029879,
        "content": "我从遥远的喵星来，陪你小半生",
        "voteup_count": 11,
        "updated_time": "2024-04-19 08:36:39",
        "question_id": 650233433,
        "user_id": "6c88e347077e8a1b42b1deadf201a97f"
    },
    {
        "answer_id": 3482732279,
        "content": "两脚兽劝你不要没事就捏我肚子",
        "voteup_count": 0,
        "updated_time": "2024-04-29 16:01:27",
        "question_id": 650233433,
        "user_id": "0d50846dfc01b03fc2b5717fff62e816"
    },
    {
        "answer_id": 3481393194,
        "content": "服气：请不要摸我不要抱我，我很爱吃猫条请多多喂我服气美照家睦：请保持厕所干净，请多多给我吃冻干，请让我抓鸟，不要让茅台出现在我面前家睦美照茅台：出去玩出去玩出去玩！好吃的好吃的好吃的！妈妈妈妈妈妈！茅台美照",
        "voteup_count": 4,
        "updated_time": "2024-04-28 12:48:07",
        "question_id": 650233433,
        "user_id": "eb6f444f12f498add70959745999c480"
    },
    {
        "answer_id": 3480858941,
        "content": "老大：妈妈每次生气都是我造成的，赶紧哈她几下给自己壮壮胆；老二：谄媚，是每个吃货获得冻干的最直接途径；老三：我最爱装萌啦，做了什么坏事，妈妈永远不会想到是我干的，多谢大哥替我出头",
        "voteup_count": 4,
        "updated_time": "2024-04-27 23:07:01",
        "question_id": 650233433,
        "user_id": "5fe2cc042295f950be0e34d103187b7e"
    },
    {
        "answer_id": 3481479200,
        "content": "楼下的鸟，别给劳资嚣张！迟早让你知道谁是这片土地的王！一只天天想下楼抓鸟的小猫",
        "voteup_count": 2,
        "updated_time": "2024-04-28 14:10:58",
        "question_id": 650233433,
        "user_id": "6840020b99226c0a948c10c2d07d272a"
    },
    {
        "answer_id": 3481489961,
        "content": "猫生得意需尽欢能躺着为什么要站着红色垃圾袋，本喵的最爱最近毛毛酷酷掉我该怎么办",
        "voteup_count": 5,
        "updated_time": "2024-04-28 14:20:43",
        "question_id": 650233433,
        "user_id": "8b95b092aca12460963ec6168605fa61"
    },
    {
        "answer_id": 3477705349,
        "content": "我的要求不多，一天两罐罐",
        "voteup_count": 4,
        "updated_time": "2024-04-25 07:46:48",
        "question_id": 650233433,
        "user_id": "a25033e50ddf6c0099df39b3467a6fb6"
    },
    {
        "answer_id": 3447494181,
        "content": "家庭条件不允许天天吃罐罐，嘤嘤嘤",
        "voteup_count": 5,
        "updated_time": "2024-03-29 11:09:50",
        "question_id": 650233433,
        "user_id": "18312e90dbcb78bdc6020c52f2221632"
    },
    {
        "answer_id": 3481616434,
        "content": "猫生就是逢场作戏",
        "voteup_count": 4,
        "updated_time": "2024-04-28 16:07:46",
        "question_id": 650233433,
        "user_id": "b4ae413fd05a3248bf72163769abe588"
    },
    {
        "answer_id": 3481661984,
        "content": "上房揭瓦，跟狗打架，云游天下……",
        "voteup_count": 1,
        "updated_time": "2024-04-28 16:46:10",
        "question_id": 650233433,
        "user_id": "1d4baeb539e9016aa19b67883713ede9"
    },
    {
        "answer_id": 3480358883,
        "content": "世上没有一只好猫，也没有一个坏人",
        "voteup_count": 2,
        "updated_time": "2024-04-27 13:12:01",
        "question_id": 650233433,
        "user_id": "158f0e2e8fa3c6cde6dc7fe01ec979e0"
    },
    {
        "answer_id": 3481245418,
        "content": "妈妈妈妈，今天的零食高低得给我了（看在我的手手伸这么长的份儿上）",
        "voteup_count": 2,
        "updated_time": "2024-04-28 10:47:11",
        "question_id": 650233433,
        "user_id": "d078792be3a7870e459da3beb41006e0"
    },
    {
        "answer_id": 3481765108,
        "content": "下次不敢了（狗头）",
        "voteup_count": 0,
        "updated_time": "2024-04-28 18:26:25",
        "question_id": 650233433,
        "user_id": "d025adc71c202744258a34ebbef9b5c8"
    },
    {
        "answer_id": 3482484853,
        "content": "不要烦我。",
        "voteup_count": 0,
        "updated_time": "2024-04-29 12:04:59",
        "question_id": 650233433,
        "user_id": "ae31cfe4cc6dab897f0a0587ca1dadc9"
    },
    {
        "answer_id": 3482082984,
        "content": "要是我能说人话就好了！吓死两脚兽哈哈哈哈～～",
        "voteup_count": 0,
        "updated_time": "2024-04-29 01:45:31",
        "question_id": 650233433,
        "user_id": "07646ed5c678358a79b09423a0c494be"
    },
    {
        "answer_id": 3482776184,
        "content": "我要吃的（超大嗓门但夹子版）！！",
        "voteup_count": 0,
        "updated_time": "2024-04-29 16:38:02",
        "question_id": 650233433,
        "user_id": "16e091cbb1ca968c8a18c8363fdfc083"
    },
    {
        "answer_id": 3482350313,
        "content": "世间是是非非，唯有鱼罐头不可辜负",
        "voteup_count": 0,
        "updated_time": "2024-04-29 10:23:15",
        "question_id": 650233433,
        "user_id": "5100f740bc6a9d1606f8cc646b528004"
    },
    {
        "answer_id": 3481517328,
        "content": "一生都要自由，也要吃饱喝足，一顿饱和顿顿饱我还是分得清的。【偶尔离家旅游，大部分混吃混喝】",
        "voteup_count": 2,
        "updated_time": "2024-04-28 14:42:57",
        "question_id": 650233433,
        "user_id": "1c9cab945a37a5218e85dd050dcad6af"
    },
    {
        "answer_id": 3480325547,
        "content": "我是家中嫡长猫",
        "voteup_count": 0,
        "updated_time": "2024-04-27 12:20:15",
        "question_id": 650233433,
        "user_id": "3a6717a5713268dc0446d7c0908870ee"
    },
    {
        "answer_id": 3480561186,
        "content": "我家妈宝喵：妈妈妈妈妈，我爱妈",
        "voteup_count": 0,
        "updated_time": "2024-04-27 16:56:44",
        "question_id": 650233433,
        "user_id": "4e33ea2ca9cc6b93a2407cff928478b0"
    },
    {
        "answer_id": 3482451804,
        "content": "已嘎蛋勿撩 ",
        "voteup_count": 0,
        "updated_time": "2024-04-29 11:35:00",
        "question_id": 650233433,
        "user_id": "aff26f484eeb9fafece0fb65b1d985dc"
    },
    {
        "answer_id": 3481955190,
        "content": "有事联系我家下属，无事告退",
        "voteup_count": 0,
        "updated_time": "2024-04-28 22:20:59",
        "question_id": 650233433,
        "user_id": "d1c41d6a4709a21ceaf5bee477900679"
    },
    {
        "answer_id": 3467028476,
        "content": "今天又是做海盗的一天。（已经去喵星很久啦）",
        "voteup_count": 9,
        "updated_time": "2024-04-15 20:02:35",
        "question_id": 650233433,
        "user_id": "39dfe96b415cea54d2dc2b911bb62793"
    },
    {
        "answer_id": 3480500782,
        "content": "麻麻，我好痛，不然真想多陪你待会儿。",
        "voteup_count": 8,
        "updated_time": "2024-04-27 15:49:17",
        "question_id": 650233433,
        "user_id": "9f76eb0fc5fc6ab2c5cf494c3fb15105"
    },
    {
        "answer_id": 3482392551,
        "content": "沙发上掉的毛，是我的思念。亦如主人的头发，是他的岁月。ε(*´･ω･)з",
        "voteup_count": 6,
        "updated_time": "2024-04-29 10:53:14",
        "question_id": 650233433,
        "user_id": "eafef45757c37db49bb67cc7b4fc100b"
    },
    {
        "answer_id": 3471603386,
        "content": "喵喵喵",
        "voteup_count": 4,
        "updated_time": "2024-04-19 16:11:16",
        "question_id": 650233433,
        "user_id": "504996770f4a345f822eae0c4ab2b09b"
    },
    {
        "answer_id": 3447450614,
        "content": "“所有好吃的都是我的”https://www.zhihu.com/video/1756994216868474880",
        "voteup_count": 4,
        "updated_time": "2024-03-29 10:41:41",
        "question_id": 650233433,
        "user_id": "a19857f09bd3432dd7dab6e4c1f48206"
    },
    {
        "answer_id": 3481384679,
        "content": "陪着主人一家走过二十个春秋，可是……得回喵星了。",
        "voteup_count": 3,
        "updated_time": "2024-04-28 12:39:24",
        "question_id": 650233433,
        "user_id": "089ef34fafccb5d6b8f24fc27328392d"
    },
    {
        "answer_id": 3448421460,
        "content": "你先给我一只猫我再回答你(　ˇωˇ)人",
        "voteup_count": 3,
        "updated_time": "2024-03-30 08:12:02",
        "question_id": 650233433,
        "user_id": "d9ea31600a46e573b181b4cb19cbe2ef"
    },
    {
        "answer_id": 3482510092,
        "content": "什么？！好容易把小铲屎官拉扯大又让我带孩子？！",
        "voteup_count": 2,
        "updated_time": "2024-04-29 12:33:40",
        "question_id": 650233433,
        "user_id": "1ba952cdb2f4da89169c6a71378fb4ed"
    },
    {
        "answer_id": 3482254036,
        "content": "哥哥：妈妈又来亲我了 好烦 （但完全没有反抗）弟弟：玩！玩！玩！嗷呜嗷呜",
        "voteup_count": 2,
        "updated_time": "2024-04-29 09:19:21",
        "question_id": 650233433,
        "user_id": "0a3b1d0a193766b03c14908912f80044"
    },
    {
        "answer_id": 3481868328,
        "content": "\"喵～喵～喵～（我饿了，要吃东西～)\"",
        "voteup_count": 3,
        "updated_time": "2024-04-28 20:38:43",
        "question_id": 650233433,
        "user_id": "7336a48e3ce2fc7db9c20763b112b81b"
    },
    {
        "answer_id": 3481681374,
        "content": "大概也会在拉屎的时候自拍？",
        "voteup_count": 2,
        "updated_time": "2024-04-28 17:02:37",
        "question_id": 650233433,
        "user_id": "1744853aadc3ff2cb001086cd178a05d"
    },
    {
        "answer_id": 3480283666,
        "content": "玛德思辨太，天天抓着我薅。强制爱泥煤啊",
        "voteup_count": 2,
        "updated_time": "2024-04-27 11:33:39",
        "question_id": 650233433,
        "user_id": "d448537422792cde70e7b7f0f4731ad5"
    },
    {
        "answer_id": 3479755894,
        "content": "“一个冷酷的杀手，迅猛的追击者”（其实我很低调）",
        "voteup_count": 2,
        "updated_time": "2024-04-26 20:14:57",
        "question_id": 650233433,
        "user_id": "fa6dbf8d86b38143389a1d23e7fac453"
    },
    {
        "answer_id": 3468632679,
        "content": "生命诚可贵，爱情价更高，若为自由固，二者皆可抛。",
        "voteup_count": 2,
        "updated_time": "2024-04-17 08:57:44",
        "question_id": 650233433,
        "user_id": "900f17e1eae7f38ede5696c440ae239f"
    },
    {
        "answer_id": 3482817401,
        "content": "第一反应就是：我妈超正！",
        "voteup_count": 1,
        "updated_time": "2024-04-29 17:11:43",
        "question_id": 650233433,
        "user_id": "836317c09115f1c571aa67e87c0c6ce9"
    },
    {
        "answer_id": 3482577083,
        "content": "社恐猫猫出gai 躲在我妹的怀里大家都看不到我 看不到我 ... ",
        "voteup_count": 1,
        "updated_time": "2024-04-29 13:44:49",
        "question_id": 650233433,
        "user_id": "9d9d787ae0307cd1dc505f22f5fead18"
    },
    {
        "answer_id": 3482502308,
        "content": "妈妈们请不要再强吻我，不要再把脸埋我胸口了！ ",
        "voteup_count": 1,
        "updated_time": "2024-04-29 12:24:23",
        "question_id": 650233433,
        "user_id": "cbf0d70a9ee9459684dc0a40eb6c3632"
    },
    {
        "answer_id": 3482224167,
        "content": "喵喵喵喵喵喵喵嗷～～喵嗷～！喵嗷～！！！嗷嗷嗷嗷嗷！！（在家就是这么叫的）",
        "voteup_count": 1,
        "updated_time": "2024-04-29 08:48:21",
        "question_id": 650233433,
        "user_id": "4a7b61b0bd382509e6b4f0f090ecca82"
    },
    {
        "answer_id": 3481935557,
        "content": "朕就是这样汉子，就是这样秉性，就是这样皇帝。尔等大臣若不负朕，朕再不负尔等也，勉之。",
        "voteup_count": 1,
        "updated_time": "2024-04-28 21:58:31",
        "question_id": 650233433,
        "user_id": "c90151735a9f6bf69b3f948888688d36"
    },
    {
        "answer_id": 3481880996,
        "content": "讨厌天天被薅猫毛",
        "voteup_count": 2,
        "updated_time": "2024-04-28 20:53:36",
        "question_id": 650233433,
        "user_id": "96ce0dd99033cddcf06b534736672a50"
    },
    {
        "answer_id": 3481856364,
        "content": "写了好多，然后又删了，因为我真是不知道的，要是问我会为我的猫写些什么，那大概就是能够早日收养她。",
        "voteup_count": 1,
        "updated_time": "2024-04-28 20:23:19",
        "question_id": 650233433,
        "user_id": "545e47eec40a9d58dff20508bf0e0189"
    },
    {
        "answer_id": 3481809114,
        "content": "今天又场地外拉了两坨爽 铲屎官应该又手舞足蹈的过来收拾了吧。",
        "voteup_count": 1,
        "updated_time": "2024-04-28 19:23:55",
        "question_id": 650233433,
        "user_id": "404d834a489a570a5ebf3be6b45bfb6e"
    },
    {
        "answer_id": 3481645974,
        "content": "肯定会写：冲着冻干方向伸个懒腰，挠一下袋子她应该知道拿冻干哄我了（一天八百个心眼子和假动作都用在要冻干上了）",
        "voteup_count": 1,
        "updated_time": "2024-04-28 16:33:13",
        "question_id": 650233433,
        "user_id": "98562d208c90aaf343bd994690bbe6dc"
    },
    {
        "answer_id": 3481433104,
        "content": "会写“今天姐姐也不回家就好了”",
        "voteup_count": 1,
        "updated_time": "2024-04-28 13:28:19",
        "question_id": 650233433,
        "user_id": "ad6c5ead6a4a2e7d06dd1729f82f1fa6"
    },
    {
        "answer_id": 3481321925,
        "content": "“憋扒拉，我敏感毛。” 每次摸她她都会很灵巧地躲开我的手啊啊啊啊气人。",
        "voteup_count": 1,
        "updated_time": "2024-04-28 11:41:28",
        "question_id": 650233433,
        "user_id": "403171a8eac69249fd51afca69a83938"
    },
    {
        "answer_id": 3481249097,
        "content": "我家的猫不亲人，不粘人，每天给她猫粮就行，给猫条不吃，给罐头不吃，就只吃猫粮，换个牌子的猫粮也不吃，饿了也不喵喵叫，就看着你，宁可饿着，你爱给不给。吃饱了更不会理你。我在卧室，她就去客厅，我去客厅，她就进卧室。如果我的猫有签名，那就是：莫挨老娘！！！（图片就是给她猫碗里掺了一点点别的牌子猫粮，闻了闻不吃，就趴着不动省力气！！！你能怎么办？）",
        "voteup_count": 1,
        "updated_time": "2024-04-28 10:49:56",
        "question_id": 650233433,
        "user_id": "6778cd585347cc615e34abd1c1848368"
    },
    {
        "answer_id": 3481238325,
        "content": "和麻麻一起玩耍是我最开心的事情",
        "voteup_count": 1,
        "updated_time": "2024-04-28 10:42:08",
        "question_id": 650233433,
        "user_id": "11b3543d1cbda6225d6f65997f58317f"
    },
    {
        "answer_id": 3480412872,
        "content": "不要老坐着，不要看手机，陪我玩，我要出玩，给我开门",
        "voteup_count": 1,
        "updated_time": "2024-04-27 14:05:16",
        "question_id": 650233433,
        "user_id": "190255f273c01cc68b77db0446e76878"
    },
    {
        "answer_id": 3480035620,
        "content": "笨蛋妈妈作妖记",
        "voteup_count": 1,
        "updated_time": "2024-04-27 05:43:08",
        "question_id": 650233433,
        "user_id": "90901c2413d7afd39d9261694757d57b"
    },
    {
        "answer_id": 3479264435,
        "content": "我要吃肉干，要好吃的冻干，要多多的，还想要小鸟。",
        "voteup_count": 1,
        "updated_time": "2024-04-26 12:38:30",
        "question_id": 650233433,
        "user_id": "ccaea7126feab7651283a37a3861d225"
    },
    {
        "answer_id": 3467205919,
        "content": "少碰我",
        "voteup_count": 1,
        "updated_time": "2024-04-15 23:17:19",
        "question_id": 650233433,
        "user_id": "7bab6ff510f8a2df3a8016faa4b20a90"
    },
    {
        "answer_id": 3458521956,
        "content": "喵～嗷～！",
        "voteup_count": 1,
        "updated_time": "2024-04-08 15:03:10",
        "question_id": 650233433,
        "user_id": "7aea7d2c19e03cb89043bfce96b27fef"
    },
    {
        "answer_id": 3482818044,
        "content": "不养人类。",
        "voteup_count": 0,
        "updated_time": "2024-04-29 17:12:19",
        "question_id": 650233433,
        "user_id": "2c68c83600b26a40f67488dcbf236ab5"
    },
    {
        "answer_id": 3482806105,
        "content": "一天三顿冻干，细细的切做臊子",
        "voteup_count": 0,
        "updated_time": "2024-04-29 17:01:38",
        "question_id": 650233433,
        "user_id": "940f779f79d904bc9b08fdd7a0ca8a84"
    },
    {
        "answer_id": 3482799605,
        "content": "喵喵喵",
        "voteup_count": 0,
        "updated_time": "2024-04-29 16:56:30",
        "question_id": 650233433,
        "user_id": "ea773841d75c29800dadb6c3d8309512"
    },
    {
        "answer_id": 3482799388,
        "content": "当我舔你的手时，请不要推开我",
        "voteup_count": 0,
        "updated_time": "2024-04-29 16:56:20",
        "question_id": 650233433,
        "user_id": "6fc1c9281b15e3ff4c8da677d6492576"
    },
    {
        "answer_id": 3482792992,
        "content": "今天我的主人换了双丑丑的拖鞋  差点没认出来嗨~ ",
        "voteup_count": 0,
        "updated_time": "2024-04-29 16:51:15",
        "question_id": 650233433,
        "user_id": "a7353cb851bd416a80320caa385988f5"
    },
    {
        "answer_id": 3482790913,
        "content": "小黑：跟我玩！西瓜：虽然我很乖，但是我很高冷。P.S.我家里有两只猫，大一点的是英短（小黑），小一点的是西瓜，小黑是她的妈妈。两只小母猫天天在家里互相作伴一起玩耍。",
        "voteup_count": 1,
        "updated_time": "2024-04-29 16:49:37",
        "question_id": 650233433,
        "user_id": "7ddb16cf219d36d939abc7ea59196a4e"
    },
    {
        "answer_id": 3482767857,
        "content": "世上哪有什么岁月静好，只是有投喂我的大猴子负重前行",
        "voteup_count": 2,
        "updated_time": "2024-04-29 16:30:45",
        "question_id": 650233433,
        "user_id": "84dc3b3b87481494a5712cf8884697d9"
    },
    {
        "answer_id": 3482757190,
        "content": "如何可以我希望是：我会陪妈妈很久很久！！【妈宝喵留】",
        "voteup_count": 0,
        "updated_time": "2024-04-29 16:21:57",
        "question_id": 650233433,
        "user_id": "b8436abf4c4906054123fb500caa4e43"
    },
    {
        "answer_id": 3482724748,
        "content": "天理昭昭，喵喵喵喵 ",
        "voteup_count": 0,
        "updated_time": "2024-04-29 15:55:17",
        "question_id": 650233433,
        "user_id": "86c49386f426459f8982dca3eadfa2f6"
    },
    {
        "answer_id": 3482684019,
        "content": "会写快给劳资猫条",
        "voteup_count": 0,
        "updated_time": "2024-04-29 15:22:17",
        "question_id": 650233433,
        "user_id": "bd662ad9b9b77687407055f244cced92"
    },
    {
        "answer_id": 3482670400,
        "content": "喵喵喵喵，喵喵喵喵！",
        "voteup_count": 0,
        "updated_time": "2024-04-29 15:10:44",
        "question_id": 650233433,
        "user_id": "d1b50b302ef68724d44ac8b8efad77b6"
    },
    {
        "answer_id": 3482661670,
        "content": "有一个光绪帝一样的主人。",
        "voteup_count": 0,
        "updated_time": "2024-04-29 15:03:28",
        "question_id": 650233433,
        "user_id": "501c3a755eaf87d632dadfbadf4af81b"
    },
    {
        "answer_id": 3482642353,
        "content": "成熟的猫猫就要自己开门出去玩☺️",
        "voteup_count": 0,
        "updated_time": "2024-04-29 14:45:50",
        "question_id": 650233433,
        "user_id": "d94b94abf25ef5e80761ea441c0880f4"
    },
    {
        "answer_id": 3482581493,
        "content": "喵喵喵，本喵拯救世界",
        "voteup_count": 0,
        "updated_time": "2024-04-29 13:48:47",
        "question_id": 650233433,
        "user_id": "e298ffced173f85a10f42839eff2c66f"
    },
    {
        "answer_id": 3482577630,
        "content": "当然是这句：劳资全天下最屌",
        "voteup_count": 0,
        "updated_time": "2024-04-29 13:45:22",
        "question_id": 650233433,
        "user_id": "bcfdd8ec3a4757625149e3fe9b15c58c"
    },
    {
        "answer_id": 3482575591,
        "content": "皇上咪驾到",
        "voteup_count": 0,
        "updated_time": "2024-04-29 13:43:15",
        "question_id": 650233433,
        "user_id": "5b6f7f97da2e5de857e042f22c8f7809"
    },
    {
        "answer_id": 3482531539,
        "content": "今天吃什么，明天吃什么",
        "voteup_count": 0,
        "updated_time": "2024-04-29 12:56:05",
        "question_id": 650233433,
        "user_id": "ff760acc03dac8a62b1718b0ce50a5cb"
    },
    {
        "answer_id": 3482477699,
        "content": "猫生如戏，罐罐快来",
        "voteup_count": 0,
        "updated_time": "2024-04-29 11:57:40",
        "question_id": 650233433,
        "user_id": "b8e512124e3af408b56cdb15fb11fce4"
    },
    {
        "answer_id": 3482469224,
        "content": "每天都有吃不完的磨牙饼干。",
        "voteup_count": 0,
        "updated_time": "2024-04-29 11:49:43",
        "question_id": 650233433,
        "user_id": "14869165ab2d31ae9c7514b1149084db"
    },
    {
        "answer_id": 3482462137,
        "content": "猫：瞅这憨货，天天没事干老拍俺",
        "voteup_count": 0,
        "updated_time": "2024-04-29 11:43:39",
        "question_id": 650233433,
        "user_id": "489708c4e4596c6c4921fc15eea22d02"
    },
    {
        "answer_id": 3482401464,
        "content": "放浪不羁，随心所欲。",
        "voteup_count": 0,
        "updated_time": "2024-04-29 10:59:07",
        "question_id": 650233433,
        "user_id": "e77c14bcd62bbaeb48010b75521d8c11"
    },
    {
        "answer_id": 3482391204,
        "content": "Oi 饭票，你怎么还没来找我",
        "voteup_count": 0,
        "updated_time": "2024-04-29 10:52:19",
        "question_id": 650233433,
        "user_id": "0e069fe62f9d6bdc68d66f7a42b63d19"
    },
    {
        "answer_id": 3482386723,
        "content": "喵",
        "voteup_count": 0,
        "updated_time": "2024-04-29 10:49:24",
        "question_id": 650233433,
        "user_id": "95246139dc6874af78929965ef5839ec"
    },
    {
        "answer_id": 3482381133,
        "content": "再来一把冻干，要鸡胸的！",
        "voteup_count": 0,
        "updated_time": "2024-04-29 10:45:20",
        "question_id": 650233433,
        "user_id": "ca5a7561e118aa7d1db2e20dddf1cf45"
    },
    {
        "answer_id": 3482331209,
        "content": "可能我家猫会说： 我喵喵喵你不是让你跟我唠嗑， 而是让你给我梳毛。",
        "voteup_count": 1,
        "updated_time": "2024-04-29 10:10:19",
        "question_id": 650233433,
        "user_id": "b8b28516da38ed46279c95342c764156"
    },
    {
        "answer_id": 3482276979,
        "content": "莫挨老子！",
        "voteup_count": 0,
        "updated_time": "2024-04-29 09:30:10",
        "question_id": 650233433,
        "user_id": "5a0754893b1ac06a04a29e6775114fbf"
    },
    {
        "answer_id": 3482232436,
        "content": "怎么会有这么蠢的两脚兽。",
        "voteup_count": 0,
        "updated_time": "2024-04-29 08:55:34",
        "question_id": 650233433,
        "user_id": "0a96df186725b6a14dc7b029c9806383"
    },
    {
        "answer_id": 3482175738,
        "content": "猫条求团购",
        "voteup_count": 0,
        "updated_time": "2024-04-29 07:56:10",
        "question_id": 650233433,
        "user_id": "cf236f15640755c812c25e5f5abed23b"
    },
    {
        "answer_id": 3482049530,
        "content": "喵喵喵喵喵喵喵",
        "voteup_count": 0,
        "updated_time": "2024-04-29 00:23:26",
        "question_id": 650233433,
        "user_id": "3efa56621afd5491565e57fb6c87391d"
    },
    {
        "answer_id": 3482036808,
        "content": " :我妈是个神经",
        "voteup_count": 0,
        "updated_time": "2024-04-29 00:04:02",
        "question_id": 650233433,
        "user_id": "333feb2e8ff044028c9ae03bc4044718"
    },
    {
        "answer_id": 3482000181,
        "content": "吃饭睡觉打豆豆",
        "voteup_count": 0,
        "updated_time": "2024-04-28 23:14:11",
        "question_id": 650233433,
        "user_id": "e12acf836c9811d3e528eee531f384cb"
    },
    {
        "answer_id": 3481991101,
        "content": "躺平",
        "voteup_count": 0,
        "updated_time": "2024-04-28 23:03:11",
        "question_id": 650233433,
        "user_id": "b5d071809f4ac903dccf6c2d1489fc47"
    },
    {
        "answer_id": 3481980113,
        "content": "喵～喵",
        "voteup_count": 0,
        "updated_time": "2024-04-28 22:49:58",
        "question_id": 650233433,
        "user_id": "be2cd45a41ffc3e142a0dd7ca36abcc2"
    },
    {
        "answer_id": 3481973585,
        "content": "来杯八宝粥",
        "voteup_count": 0,
        "updated_time": "2024-04-28 22:42:31",
        "question_id": 650233433,
        "user_id": "96c07272f96b7b7e7033380fd133c6df"
    },
    {
        "answer_id": 3481957321,
        "content": "任何风吹草动，都打破不了我对你的心",
        "voteup_count": 0,
        "updated_time": "2024-04-28 22:23:35",
        "question_id": 650233433,
        "user_id": "c8efd392bcf543116b96789f81eb7b58"
    },
    {
        "answer_id": 3481955600,
        "content": "让我进屋！喵呜呜呜呜呜呜～",
        "voteup_count": 0,
        "updated_time": "2024-04-28 22:21:30",
        "question_id": 650233433,
        "user_id": "f3d7cd1a0f157acc01fd2ce9c31f1d23"
    },
    {
        "answer_id": 3481947476,
        "content": "我妈是世界上最美丽的女人(没被威胁）",
        "voteup_count": 0,
        "updated_time": "2024-04-28 22:12:19",
        "question_id": 650233433,
        "user_id": "4d430ab51e8934f0442580dbca4db229"
    },
    {
        "answer_id": 3481894089,
        "content": "有妈的孩子是个宝",
        "voteup_count": 0,
        "updated_time": "2024-04-28 21:09:04",
        "question_id": 650233433,
        "user_id": "cd64c955fd8a8d3f4bd7c1fa0368e4b4"
    },
    {
        "answer_id": 3481849576,
        "content": "我妈是个大懒批，我天天饿肚子",
        "voteup_count": 0,
        "updated_time": "2024-04-28 20:14:44",
        "question_id": 650233433,
        "user_id": "d68648b1c0d6de6f9f847445b785b936"
    },
    {
        "answer_id": 3481847397,
        "content": "滚尼玛。",
        "voteup_count": 0,
        "updated_time": "2024-04-28 20:12:15",
        "question_id": 650233433,
        "user_id": "8450350164780432732a85167617ece4"
    },
    {
        "answer_id": 3481826817,
        "content": "天下第一神经病就是我！噢耶✌ ",
        "voteup_count": 0,
        "updated_time": "2024-04-28 19:46:16",
        "question_id": 650233433,
        "user_id": "d8c11be7dad4477e2839ab8ff1099687"
    },
    {
        "answer_id": 3481826535,
        "content": "“妈妈，我晚点回来，记得给我留饭",
        "voteup_count": 0,
        "updated_time": "2024-04-28 19:45:53",
        "question_id": 650233433,
        "user_id": "f714dfca287db70d9c003769d76c405d"
    },
    {
        "answer_id": 3481767031,
        "content": "爱吃湿粮",
        "voteup_count": 0,
        "updated_time": "2024-04-28 18:29:10",
        "question_id": 650233433,
        "user_id": "7abec88f0c823d92d85524f13287b804"
    },
    {
        "answer_id": 3481738730,
        "content": "黑猫警长本长，从业十余年战绩可查。",
        "voteup_count": 0,
        "updated_time": "2024-04-28 17:56:39",
        "question_id": 650233433,
        "user_id": "880cad38d0c0aca8fd6c3dcfe1b6ce9d"
    },
    {
        "answer_id": 3481692185,
        "content": "莫打扰我睡觉",
        "voteup_count": 0,
        "updated_time": "2024-04-28 17:11:51",
        "question_id": 650233433,
        "user_id": "c7194092760903aeedc58882b19099aa"
    },
    {
        "answer_id": 3481683726,
        "content": "“吃饭睡觉捣乱”",
        "voteup_count": 0,
        "updated_time": "2024-04-28 17:04:35",
        "question_id": 650233433,
        "user_id": "4805d35187d601f76922cf0522ab0cd3"
    },
    {
        "answer_id": 3481675578,
        "content": "我喜欢咬妈妈，虽然每次都挨削",
        "voteup_count": 0,
        "updated_time": "2024-04-28 16:57:38",
        "question_id": 650233433,
        "user_id": "18e0b07607fb904cecfb795ad3700a39"
    },
    {
        "answer_id": 3481670577,
        "content": "让我一次睡个够 ",
        "voteup_count": 0,
        "updated_time": "2024-04-28 16:53:15",
        "question_id": 650233433,
        "user_id": "a88de7af6cfbc1feb693db42cc54229e"
    },
    {
        "answer_id": 3481656092,
        "content": "猫条没撕开，别想骗我过去，我聪明着呢",
        "voteup_count": 0,
        "updated_time": "2024-04-28 16:41:26",
        "question_id": 650233433,
        "user_id": "c2627efa9e62438c1f30623e68f69897"
    },
    {
        "answer_id": 3481638111,
        "content": "落日晚风尽头，我要多自由多自由",
        "voteup_count": 0,
        "updated_time": "2024-04-28 16:26:25",
        "question_id": 650233433,
        "user_id": "a912b9acf4eb8bde1c10547e22cd6d22"
    },
    {
        "answer_id": 3481618213,
        "content": "奶奶有魔法，手里总能变出好吃的",
        "voteup_count": 0,
        "updated_time": "2024-04-28 16:09:24",
        "question_id": 650233433,
        "user_id": "0e862f1d1250229ea8ff53e5f8f9ba1e"
    },
    {
        "answer_id": 3481585489,
        "content": "喵喵喵，喵喵喵喵。",
        "voteup_count": 0,
        "updated_time": "2024-04-28 15:41:28",
        "question_id": 650233433,
        "user_id": "8c2bce5779e21bb8487a931f93403069"
    },
    {
        "answer_id": 3481581237,
        "content": "一觉醒来，又是无聊的一天 ",
        "voteup_count": 0,
        "updated_time": "2024-04-28 15:37:47",
        "question_id": 650233433,
        "user_id": "9cabc3a04b3d5524f195d3324826131e"
    },
    {
        "answer_id": 3481541954,
        "content": "喵～",
        "voteup_count": 0,
        "updated_time": "2024-04-28 15:04:00",
        "question_id": 650233433,
        "user_id": "c9515b1a497507927e46e562cd7c4719"
    },
    {
        "answer_id": 3481518087,
        "content": "喵",
        "voteup_count": 0,
        "updated_time": "2024-04-28 14:43:32",
        "question_id": 650233433,
        "user_id": "44ec9a165a170c2674b905e0f26d5f09"
    },
    {
        "answer_id": 3481504671,
        "content": "高冷布偶公公，它只会说“莫挨老子”",
        "voteup_count": 0,
        "updated_time": "2024-04-28 14:33:01",
        "question_id": 650233433,
        "user_id": "ff19dbb67627fe99d6546cd5974f9203"
    },
    {
        "answer_id": 3481504631,
        "content": "给我猫条，一猫条一撸。",
        "voteup_count": 0,
        "updated_time": "2024-04-28 14:32:59",
        "question_id": 650233433,
        "user_id": "32bb76c33000ee2ea7177bb2ee1f94d1"
    },
    {
        "answer_id": 3481502741,
        "content": "吃喝不愁就是光棍的命",
        "voteup_count": 0,
        "updated_time": "2024-04-28 14:31:40",
        "question_id": 650233433,
        "user_id": "a84e5f155c051897ba604b30e8c8353a"
    },
    {
        "answer_id": 3481483020,
        "content": "外面的世界好可怕（瑟瑟发抖~）",
        "voteup_count": 0,
        "updated_time": "2024-04-28 14:14:25",
        "question_id": 650233433,
        "user_id": "4b1e00c1ee5d2afd21c17d6d6a29bcfb"
    },
    {
        "answer_id": 3481474433,
        "content": "大家好，我是猫",
        "voteup_count": 0,
        "updated_time": "2024-04-28 14:06:44",
        "question_id": 650233433,
        "user_id": "b5648efb7c46631b7eeb79d8187fd811"
    },
    {
        "answer_id": 3481429996,
        "content": "我是猫猫，我怕谁",
        "voteup_count": 0,
        "updated_time": "2024-04-28 13:25:11",
        "question_id": 650233433,
        "user_id": "595982ca332a7857497d95d0effccf7f"
    },
    {
        "answer_id": 3481409978,
        "content": "弄死主人的100种方法",
        "voteup_count": 0,
        "updated_time": "2024-04-28 13:04:43",
        "question_id": 650233433,
        "user_id": "30bf7ef5b668d514d0bd246e448ddf58"
    },
    {
        "answer_id": 3481350122,
        "content": "夏天热热，不准抱抱",
        "voteup_count": 0,
        "updated_time": "2024-04-28 12:03:57",
        "question_id": 650233433,
        "user_id": "0d2ee26b1185507fa9bd2345d879afbf"
    },
    {
        "answer_id": 3481332878,
        "content": "狗子真烦，想把它扔出去。",
        "voteup_count": 0,
        "updated_time": "2024-04-28 11:49:55",
        "question_id": 650233433,
        "user_id": "725e928dafef81f79a089957f04e0cd2"
    },
    {
        "answer_id": 3481312335,
        "content": "查过了，写的是：吃醋媞洇ゐ涐囍欢你，甡芞媞洇ゐ涐怪苸你，发梅媞洇ゐ涐想你，伤吣呮媞洇ゐ涐卟想矢呿你根据人猫年龄换算法计算的话，他大概是一只90后猫咪",
        "voteup_count": 1,
        "updated_time": "2024-04-28 11:34:22",
        "question_id": 650233433,
        "user_id": "3564fa6aabb123ecc8a8c4305bb5e9ea"
    },
    {
        "answer_id": 3481307007,
        "content": "罐罐拿来，退朝~",
        "voteup_count": 0,
        "updated_time": "2024-04-28 11:30:18",
        "question_id": 650233433,
        "user_id": "f1a6db15147c96005a657609f451ee56"
    },
    {
        "answer_id": 3481195300,
        "content": "喵",
        "voteup_count": 0,
        "updated_time": "2024-04-28 10:11:04",
        "question_id": 650233433,
        "user_id": "6b3097559cc678eedb441230ea8b6ebd"
    },
    {
        "answer_id": 3481044124,
        "content": "让爷透批",
        "voteup_count": 0,
        "updated_time": "2024-04-28 07:53:26",
        "question_id": 650233433,
        "user_id": "cbc76ad10edb5a0c35fbaa788b5ad29a"
    },
    {
        "answer_id": 3480958538,
        "content": "莫挨老子",
        "voteup_count": 0,
        "updated_time": "2024-04-28 01:53:19",
        "question_id": 650233433,
        "user_id": "9c12fe550e41933f61e671d2b8df36d1"
    },
    {
        "answer_id": 3480903768,
        "content": "放下助猫情结 尊重他猫命运",
        "voteup_count": 0,
        "updated_time": "2024-04-28 00:02:02",
        "question_id": 650233433,
        "user_id": "1a5e11b64384d009d40fb3243db6f1b1"
    },
    {
        "answer_id": 3480881599,
        "content": "猫生在世，吃喝二字（手动狗头）",
        "voteup_count": 0,
        "updated_time": "2024-04-27 23:33:33",
        "question_id": 650233433,
        "user_id": "aa2cebde45883400f2ed50d9fb03efdf"
    },
    {
        "answer_id": 3480768322,
        "content": "拜托主人给我开罐罐",
        "voteup_count": 0,
        "updated_time": "2024-04-27 21:24:49",
        "question_id": 650233433,
        "user_id": "214c0322f4a8bdc4d6891a1fe98a70c5"
    },
    {
        "answer_id": 3480744167,
        "content": "还不回来！这么晚还不回来！！",
        "voteup_count": 0,
        "updated_time": "2024-04-27 20:57:00",
        "question_id": 650233433,
        "user_id": "af1957ba07e1667e9a2576e1481b3d29"
    },
    {
        "answer_id": 3480646885,
        "content": "舔狗勿扰！ ",
        "voteup_count": 0,
        "updated_time": "2024-04-27 18:46:48",
        "question_id": 650233433,
        "user_id": "234323622be2d6e828dabfb6d46ccd90"
    },
    {
        "answer_id": 3480608201,
        "content": "猫爪之下，皆是臣民",
        "voteup_count": 0,
        "updated_time": "2024-04-27 17:53:10",
        "question_id": 650233433,
        "user_id": "3569cd5f7c5d15fc9c00abe6e579506e"
    },
    {
        "answer_id": 3480529347,
        "content": "我不喜欢鸡肉罐罐！",
        "voteup_count": 0,
        "updated_time": "2024-04-27 16:20:13",
        "question_id": 650233433,
        "user_id": "a734e7054c87bf7914e80d0de80ec567"
    },
    {
        "answer_id": 3480524512,
        "content": "妈妈怎么还不回来.",
        "voteup_count": 0,
        "updated_time": "2024-04-27 16:14:49",
        "question_id": 650233433,
        "user_id": "7abd9935a4ccf2abbdab3fcb732b9efd"
    },
    {
        "answer_id": 3480504528,
        "content": "猫傻罐头多，喜欢交朋友，女猫优先",
        "voteup_count": 0,
        "updated_time": "2024-04-27 15:53:20",
        "question_id": 650233433,
        "user_id": "3faa9d06821a7abd3053203569e4c237"
    },
    {
        "answer_id": 3480248402,
        "content": "又是想吃猫条的一天~",
        "voteup_count": 0,
        "updated_time": "2024-04-27 10:59:59",
        "question_id": 650233433,
        "user_id": "7dc7acd6c893a8ceee86b568c8b1cde7"
    },
    {
        "answer_id": 3480167096,
        "content": "喵呜！奇怪的人类！（老天奶）",
        "voteup_count": 0,
        "updated_time": "2024-04-27 09:41:34",
        "question_id": 650233433,
        "user_id": "e66db4713554aa29e281c7ab23823525"
    },
    {
        "answer_id": 3480132169,
        "content": "我每天都在我妈的头上胡作非为",
        "voteup_count": 0,
        "updated_time": "2024-04-27 09:04:37",
        "question_id": 650233433,
        "user_id": "05319c00425cce8ef03bf05cd5fd75bd"
    },
    {
        "answer_id": 3480121818,
        "content": "我是妈妈的大宝妞",
        "voteup_count": 0,
        "updated_time": "2024-04-27 08:51:52",
        "question_id": 650233433,
        "user_id": "8e24b7a6ee4fa064bde4a8418185652e"
    },
    {
        "answer_id": 3480111705,
        "content": "格老子的，放我出去",
        "voteup_count": 0,
        "updated_time": "2024-04-27 08:39:47",
        "question_id": 650233433,
        "user_id": "7446b25a2a40371b49affd12b4d9288c"
    },
    {
        "answer_id": 3480096202,
        "content": "我不是真的人，但她是真的狗。",
        "voteup_count": 0,
        "updated_time": "2024-04-27 08:19:25",
        "question_id": 650233433,
        "user_id": "22a93da8f6dc969f17f8b26fb1d44835"
    },
    {
        "answer_id": 3480092982,
        "content": "我要求每天都吃冻干！吃冻干！吃冻干！",
        "voteup_count": 0,
        "updated_time": "2024-04-27 08:15:10",
        "question_id": 650233433,
        "user_id": "32b4aea5f2b5a33ba09d65d794c36d73"
    },
    {
        "answer_id": 3480089573,
        "content": "守护两脚兽。",
        "voteup_count": 0,
        "updated_time": "2024-04-27 08:10:24",
        "question_id": 650233433,
        "user_id": "06c12b99cbbfb255ecf0bbb35e7997d4"
    },
    {
        "answer_id": 3479914297,
        "content": "莫挨老子",
        "voteup_count": 0,
        "updated_time": "2024-04-26 23:25:38",
        "question_id": 650233433,
        "user_id": "1f4a75f897f8c5abebe3258b38952e84"
    },
    {
        "answer_id": 3479682220,
        "content": "欢迎关注永雏塔菲喵，谢谢喵",
        "voteup_count": 0,
        "updated_time": "2024-04-26 18:38:00",
        "question_id": 650233433,
        "user_id": "ccfbb07e9fb0369fac3f93d8e8338e42"
    },
    {
        "answer_id": 3479564639,
        "content": "放我出去玩",
        "voteup_count": 0,
        "updated_time": "2024-04-26 16:47:46",
        "question_id": 650233433,
        "user_id": "7927dbc5b19fcdde33724572b2751324"
    },
    {
        "answer_id": 3479356218,
        "content": "切。",
        "voteup_count": 0,
        "updated_time": "2024-04-26 14:03:11",
        "question_id": 650233433,
        "user_id": "e1a1a81bdb154532ce5cb04dbf00afa4"
    },
    {
        "answer_id": 3459579625,
        "content": "猫生",
        "voteup_count": 0,
        "updated_time": "2024-04-09 12:09:44",
        "question_id": 650233433,
        "user_id": "664f8fe5da2a6869aa9eb0ce097921ca"
    },
    {
        "answer_id": 3481418846,
        "content": "知乎的提问越来越无聊",
        "voteup_count": 0,
        "updated_time": "2024-04-28 13:13:48",
        "question_id": 650233433,
        "user_id": "2508c2c62e71634986be33758642137b"
    }
]