[
    {
        "answer_id": 3475219551,
        "content": "windows11默认开启基于VT-x的内核防护这是表示windows11不支持运行这个游戏吗？",
        "voteup_count": 474,
        "updated_time": "2024-04-23 02:00:37",
        "question_id": 653529000,
        "user_id": "44628751c3f5c97f8666767bdbd70866"
    },
    {
        "answer_id": 3473954673,
        "content": "叹为观止，这也太长管太宽了，向日葵这种都算上了，顶着这玩意真能打fps吗？",
        "voteup_count": 396,
        "updated_time": "2024-04-21 23:08:50",
        "question_id": 653529000,
        "user_id": "bae303807a8173cab2b3122b335fc67c"
    },
    {
        "answer_id": 3475563213,
        "content": "奇怪了。。这游戏就非玩不可吗？",
        "voteup_count": 231,
        "updated_time": "2024-04-23 11:10:32",
        "question_id": 653529000,
        "user_id": "804a12f92a9623ed4c6db5c47e85cfe0"
    },
    {
        "answer_id": 3476171048,
        "content": "对我没有任何影响，因为我一直以来都抵制所有名为购买实为租用的软件，并且愿意借此机会再次推广一波http://gog.com。而你在鹅肠的所有游戏里花的每一分钱，都没有“购买”到任何东西，因为：2.6 游戏账号是腾讯按照本协议授权您用于登录、使用腾讯游戏及相关服务的标识和凭证，其所有权属于腾讯。珍爱生命，远离鹅肠。",
        "voteup_count": 390,
        "updated_time": "2024-04-24 10:21:48",
        "question_id": 653529000,
        "user_id": "630612ff80641e9ec165af192743a792"
    },
    {
        "answer_id": 3477195725,
        "content": "早在过去，3Q大战那段时间，腾讯就可以做到，运行QQ后，只要检测到电脑上有360的软件，就会停止运行，逼着用户“二选一”。最后是工信部出面要求互相兼容。在这里我不想讨论这件事情的对错，只是在陈述这件事情。家里的电脑上装了两个腾讯的游戏，也装了向日葵，都是有需要才启动。之前腾讯在打击CF外挂的公告里面就有提过，有用户因为在游戏时开着远程软件导致封号。腾讯发这个公告，我不得不产生一个担忧。现在只是发个公告这么说，以后为了反外挂，会不会像当年3Q大战一样，要求用户卸载这些软件才能运行游戏。这个公告一出，反倒是暴露了他们反外挂的无能。我能做的，就是尽可能不玩腾讯后续推出的游戏。——————————另外我看到了硬件限制里面有分线器，在这里提出两个疑问：1、这里的分线器，是否包括USB分线器？台式机上面使用延长线+分线器，将机箱后面的接口转接过来，算合理需求吧。2、如果包括，一些笔记本电脑的外围设备，比如摄像头、触摸板，在设备管理器里面，走的是USB集线器的端口，那么是不是将不允许这部分笔记本电脑启动游戏？",
        "voteup_count": 51,
        "updated_time": "2024-04-24 17:14:22",
        "question_id": 653529000,
        "user_id": "6ebd5269f9ba00aede2cbe614ec840e7"
    },
    {
        "answer_id": 3476154711,
        "content": "影响？不会真有人能玩外服情况下还玩马服吧省服体验可比马服好多了外服那个开机自启动的反作弊都没这么多b事，不影响你开ce改其他游戏",
        "voteup_count": 187,
        "updated_time": "2024-04-23 19:52:12",
        "question_id": 653529000,
        "user_id": "5a8c98dff1c891c91234aa3242de58bc"
    },
    {
        "answer_id": 3476457939,
        "content": "3Q大战犹在眼前。不行开游戏直接扫盘检测环境吧，再现往日有我没他之风。看看列表里几个软柿子，能不能跨省跨国抓了。",
        "voteup_count": 104,
        "updated_time": "2024-04-24 05:26:21",
        "question_id": 653529000,
        "user_id": "9ba41b7ec25390bd23e1703a95017c16"
    },
    {
        "answer_id": 3476365228,
        "content": "强烈建议Windows12强制启用VBS/HVCI，禁止任何驱动篡改NT只读区域内存。VBS是Xbox one和Xbox seres X|S使用的安全技术，通过Hyper-V虚拟化技术确保内核页面的权限和内容不被篡改，阻止了恶意驱动程序修改NT关键内存，防止驱动hook系统调用；通过强制启用IOMMU阻止了外置DMA硬件读取系统内存。在启用了VBS之后，大部分影响系统稳定性的反作弊驱动，以及大部分驱动级、硬件级作弊手段同时失效，避免用户的电脑成为攻防双方的战场。基于虚拟化的安全 (VBS)大家好像理解错了，强制启用VBS不代表用户不能禁用VBS，就像Windows11也强制要求启用安全启动一样，这个和TPM是不一样的。强制启用VBS的目的为AMD等厂商必须解决VBS产生的卡顿、性能损失等情况任何试图获得WHQL签名的驱动必须兼容VBS",
        "voteup_count": 259,
        "updated_time": "2024-04-24 22:37:03",
        "question_id": 653529000,
        "user_id": "5687234f176a34d8890ae0dc1811c119"
    },
    {
        "answer_id": 3476666191,
        "content": "《无畏契约》因其反作弊软件Vanguard而招致批评，因为该软件显示运行在内核驱动程序上，该内核驱动程序允许访问计算机系统。OSNews担心Riot Games及其所有者腾讯可能监视用户数据，并且内核驱动程序可能会被第三方利用。禁止的这些东西呢，很大一部份就是比较危险的第三方。所以最好的方法呢，就是不玩国服。当然了，从炉石传说关闭国服之后的表现来看。绝大多数玩家，能打开游戏已经很给力了。至于工作室的话，他们不怕你封号。",
        "voteup_count": 46,
        "updated_time": "2024-04-24 10:06:00",
        "question_id": 653529000,
        "user_id": "222ac4b81de4de96cff57c90a34b96c7"
    },
    {
        "answer_id": 3476447230,
        "content": "合着proc mon（process monitor）、windbg在鹅厂的大佬看来，也成黑客工具了？微软自己给用户做用来黑Windows的黑客工具是吧？另外要是谁能用ce把你反作弊破了，我建议你鹅肠还是回炉重造吧。最重要的，禁止虚拟化未免也太tm离谱了。win11默认开内核隔离启用hyperv，现在主流虚拟机软件和杀毒软件都兼容了（不过不少知友都说外服游戏反作弊也检测虚拟化了，越来越离谱了；但我之前esay anticheat的游戏开了hyperv可以玩，gta也不影响）。要是开个虚拟机环境就不能玩游戏了，我肯定卸游戏，因为我要用虚拟机和wsl。而且你这也不建议用，那也不建议用。我是不是后台向日葵/to desk/steam开机自启，或者nsight 查看之前跑的性能数据忘记关了，你就有封我号的理由了？最后奉劝游戏厂商搞清楚反作弊的本质。反作弊本身是为了在基本不影响用户体验的前提下，提高作弊的成本；而不是为了减少作弊，直接让所有用户去适应你的反作弊系统。举个例子，当初Windows defender作为Windows自带杀毒，资源占用严重卡的人受不了不说，还查杀率低的同时误杀严重，以至于没有几个想不开的会用（虽然现在还行）。所以别把自己手里的（代理的）游戏太当回事。你整的这些幺蛾子，都会造成实打实的玩家流失，毕竟现在游戏这么多，你不让我玩网游有的是单机/联机游戏让我玩。就算你反作弊软件做的再牛逼，能让一切软件外挂失效，我直接获取hdmi信号输出，另一台电脑ai锁头，单片机模拟键鼠发io信号，计算机上没有任何非法软硬件，请问你怎么检测？",
        "voteup_count": 307,
        "updated_time": "2024-04-24 15:04:46",
        "question_id": 653529000,
        "user_id": "4cd4aa67e569ba81aef609a8041dbbbe"
    },
    {
        "answer_id": 3475431065,
        "content": "老馋",
        "voteup_count": 85,
        "updated_time": "2024-04-23 09:42:51",
        "question_id": 653529000,
        "user_id": "2159b7f6c2dce2ea4877809bb223c2d8"
    },
    {
        "answer_id": 3476547545,
        "content": "Python脚本不知道腾讯会用什么方法去禁用，如果是扫盘检测到安装或者运行了Python就开始弹窗，那几乎所有Python开发者甚至是计算机行业的人都要告别腾讯游戏了。而且Python也不一定只能是计算机行业在使用，金融，科研，工业方面的行业多多少少会有一定的交集，做个表格都会有很多人用Python脚本，到最后不受影响的只有不事生产的电脑小白了。这个也不是最近一两天的事情，以前的腾讯软件就有类似的行为，只不过现在又加码了，到了这种地步，腾讯还不如推出一款腾讯游戏专用主机，因为现在这种行为已经相当于把你的电脑霸占了，涉及了那么多日常工具，得自己一个个去排查，一旦开完不小心关就爆炸，在这之前就有很多玩腾讯游戏的，用按键精灵去其他游戏挂机，结果回来之后发现腾讯那边的账号被封了。自己没这技术去反外挂，就用这种下三滥的手段来恶心玩家，又不是什么旷世神作，不玩也罢。还有个比较坏的影响，他把这些开挂方法公布出来，更多的人知道这些工具，你倒是封住了，别的游戏呢，这你这里用不了又跑去其他游戏里面用，间接破坏其他游戏环境，属于是游戏界的和污染水了。即使做得再极端，也不能一劳永逸，模拟插件的使命就是干这个的，肯定不会束手就擒，别人团队也会跟进，最后结局就是用户的电脑变成双方战场。仁义之师：小心推进，精准杀敌，尽量不伤害平民。马家军：你的电脑里面存在有大量恐怖分子，不管三七二十一，开大飞机炸弹洗地，恐怖分子没炸死几个，你的电脑倒是被炸得千苍百孔。",
        "voteup_count": 60,
        "updated_time": "2024-04-25 18:51:17",
        "question_id": 653529000,
        "user_id": "91d53b8fea610fea553258969f370e76"
    },
    {
        "answer_id": 3476378455,
        "content": "腾子这么多年了依然不忘初心，还是那个3q大战的腾子，令人感慨",
        "voteup_count": 82,
        "updated_time": "2024-04-24 00:06:38",
        "question_id": 653529000,
        "user_id": "d373850c1f88fe17413cee344c93dd56"
    },
    {
        "answer_id": 3474797137,
        "content": "这年头，还有不带鼠标宏的鼠标吗？",
        "voteup_count": 71,
        "updated_time": "2024-04-22 17:08:27",
        "question_id": 653529000,
        "user_id": "a1d27a65e4f025a731625d0421fc3bd7"
    },
    {
        "answer_id": 3476472015,
        "content": "我来解释一下，给小白科普科普：一般来说私人工作室都是自己写调试器，实现ce那些功能并不难，单纯禁止市面上流行的没啥意义。禁止vt那是是禁止vt虚拟化的外挂，vt虚拟化可以实现无痕hook，对于有crc检验的游戏打击很大。dma这个就是用fpga走dma通道，直接读取游戏数据，伪装成网卡声卡，本身就是一个硬件，基本没法防御，但人工截图还是可以的，笑。剩下那个那个应该是玩易语言的搞得，就是利用识图，然后对比图像，虽然粗糙了点。按键精灵那个已经过时了，现在都是在0环对抗，3环那些东西没啥意义。外挂产业链也分很多环，最赚钱的是卖调试器的，就好比淘金热里卖铲子的，至于剩下在游戏里找数据的，纯属体力活，fps算是被dma挂这玩意给毁了，其他用vt虚拟化的也算是到了技术的尽头，不过随着pc网游市场的萎缩，游戏收益下降，搞外挂的人也就越来越少啦，不用太担心。pchunter一般用来查看游戏厂商hook了哪些api，但是hook的位置比较深可能需要手动对比windbg是ms的内核调试工具，windows也和单片机一样可以用调试器调试那些乱七八糟的dbg就是魔改过加了驱动的x64dbgvt虚拟化我记得是intel搞得",
        "voteup_count": 32,
        "updated_time": "2024-04-24 06:50:19",
        "question_id": 653529000,
        "user_id": "57e39c9ed56e7925b1d8a32ebd425009"
    },
    {
        "answer_id": 3476332530,
        "content": "有种禁止访问以下网站的美。也算是给小白科普了一下有这么多功能不同的好用工具，功德无量。",
        "voteup_count": 78,
        "updated_time": "2024-04-23 23:11:12",
        "question_id": 653529000,
        "user_id": "9bdebeb7644b48ec9a7c701b516be723"
    },
    {
        "answer_id": 3476581625,
        "content": "window11 默认开启基于VT-x的内核防护。Todesk、向日葵、TeamViewer，这类远程工具很常用，为应对客户的突发情况，个人电脑上也会装。VMWare，大部分码农都会装吧WinPix、NVIDIA Nsight、Intel GPA这类工具，感觉是Windows，NVIDIA显卡，Intel自带的功能玩个游戏还要带赛博枷锁",
        "voteup_count": 22,
        "updated_time": "2024-04-24 09:05:03",
        "question_id": 653529000,
        "user_id": "908dc424fdfa3db04ac4503831b14e9d"
    },
    {
        "answer_id": 3476460897,
        "content": "这事还真不全怪腾子，因为它一开始就是拳头搞的。当年瓦还在B测的时候我就因为装了那拟态反作弊系统导致VMWare虚拟机开不了机了。当时我根本找不到原因，在stack overflow上问了半天，终于在找到某条帖子下面找到一条评论说兄弟你是不是下瓦罗兰特了。我试着把瓦给卸了，然后就好了。所以现在腾子能够公布哪些软硬件可能碰到问题已经不错了，当年我可是折腾了好久才找到原因。前段时间玩The Finals也是，因为我后台挂着CE，小蓝熊检测到了，游戏一进去我一把都还没打直接给我号封了，官网申诉也是等了一星期才给我解封。现在我开游戏前都要检查一下CE关没关了。",
        "voteup_count": 33,
        "updated_time": "2024-04-24 05:41:50",
        "question_id": 653529000,
        "user_id": "e48cf45af5fe0c9bb1dc9f86fffb010d"
    },
    {
        "answer_id": 3476469483,
        "content": "现在还不会开的，知道搜什么关键词了吧？开挂指南给你放这了。",
        "voteup_count": 34,
        "updated_time": "2024-04-24 06:22:25",
        "question_id": 653529000,
        "user_id": "8e5f63079664e3ff7c2c6c2aed7225d4"
    },
    {
        "answer_id": 3473493561,
        "content": "也就国内敢公开的这样写.世界上最好欺负的一批\"人\".",
        "voteup_count": 151,
        "updated_time": "2024-04-21 14:01:08",
        "question_id": 653529000,
        "user_id": "fb380fb72f303063c64c712070c558a9"
    },
    {
        "answer_id": 3476687830,
        "content": "《无畏契约》是啥？",
        "voteup_count": 24,
        "updated_time": "2024-04-24 10:20:25",
        "question_id": 653529000,
        "user_id": "87be8364c5490b6e546ff591649e9763"
    },
    {
        "answer_id": 3479016906,
        "content": "我弃玩星铁就是因为它装了tpprotect这逼东西把我的任务管理器识别为有问题的软件tx是业界毒瘤",
        "voteup_count": 9,
        "updated_time": "2024-04-26 09:31:51",
        "question_id": 653529000,
        "user_id": "96efeb23666d37c07a74b85c3ccfac7c"
    },
    {
        "answer_id": 3476850041,
        "content": "好家伙，虚拟化给禁了是最强的，那我估计可能有六成Windows 11用户玩不了这游戏了评价是不会反外挂就别整烂活，你不如出个腾讯游戏专属主机定制系统彻底杜绝外挂",
        "voteup_count": 58,
        "updated_time": "2024-04-24 12:16:56",
        "question_id": 653529000,
        "user_id": "52296f6b4927636fc8b8887bbd86fb2e"
    },
    {
        "answer_id": 3480458507,
        "content": "本来想为了反作弊做出点代价还是能接受的，打开问题描述我绷不住了。不光是搞计算机的频频中枪，这里面很多软件都是日常民用的软件，尤其是诸多远程桌面或串流工具，很多软件为了使用方便都是后台自动值守的，这么一搞每次开游戏还得小心翼翼的把所有这些软件的后台清理，要是清不干净没准就封号了。最关键的是，因为很多软件十分常用，大多数对计算机缺乏了解的人可能并不清楚后台是否正在运行相关进程，就和马家的旧版QQ一样，退出登陆了后台有时候还会拉起一个qqprotect.exe，防不胜防。而且一些东西可能是在你不知道的情况下运行的：比如Python脚本，很多软件都会带一个Python，在后台用Python处理一些简单的逻辑，不打开任务管理器你很难发现这些，没准就中招了。比如Steam Link的服务端是集成到Steam当中的，按我的理解想要玩《无畏契约》还必须得把Steam卸载干净，不然也可能被封号。比如虚拟化，Windows11默认开启基于VT-x虚拟化的内核防护，一台全新的Windows电脑打开游戏就有被封号的可能。为了玩你一个游戏各位还得先在任务管理器里仔细清理，人均化身进程调试员。而作为普通人，唯一能放心的方案就是买一台电脑单独玩《无畏契约》，这台电脑还不能装别的软件或游戏，因为你不知道哪个软件就趟雷了。即便这样还不行，因为一个干净的Windows默认环境也存在被封号的风险，你还得学会如何关闭VT-x虚拟化。我自己现在都不明白一件事，就是这个带宏脚本的鼠标，现在大多数主流品牌的鼠标都支持鼠标宏，所以我还得抛弃我的鼠标，去买一个完全不带宏的鼠标，这在现在怕不是有点困难。当然，也许有人会说腾讯不会限制的这么死板，但现实是这些内容写在了游戏官网，也没说判定的标准：无畏契约禁止/不建议使用的软硬件列表-VALORANT《无畏契约》官方网站-腾讯游戏“刑不可知则威不可测”，大家在日常生活中已经被这句话伤的够透的了，玩游戏是放松来的，反正我是不想头上悬一个达摩克里斯之剑。当然，还是希望腾讯能多贴近一下玩家，不然也就别自以为是的在那自我批评了，你们不失败谁失败？",
        "voteup_count": 13,
        "updated_time": "2024-04-27 15:06:19",
        "question_id": 653529000,
        "user_id": "aa2c3d85e198c18c41e95e1e4032696a"
    },
    {
        "answer_id": 3476492674,
        "content": "个人感觉有点太过度了。简单一看禁止使用的列表里面就已经有我日常使用的工具了。1、分线器 ：这个对于外设多的玩家来说简直太重要了，我插个键盘、手臂、耳机、鼠标、音箱而已，这样我就是外挂了？2、OBS：这个我常常在玩游戏的时候开着录屏功能，游戏视频素材获取的顶尖工具也是外挂了？等等，貌似我不玩《无畏契约》。那没事了，腾讯安全中心威武！反对一切外挂！",
        "voteup_count": 65,
        "updated_time": "2024-04-24 07:23:41",
        "question_id": 653529000,
        "user_id": "6dafeb55f22168236c736dfcf8a95d5f"
    },
    {
        "answer_id": 3476468328,
        "content": "我在想，伪装成正常硬件（比如一个网卡）的恶意DMA PCIe硬件，你怎么检测出来？",
        "voteup_count": 28,
        "updated_time": "2024-04-24 06:18:06",
        "question_id": 653529000,
        "user_id": "fa7c5cf9700340e0aa0055e55f01f4b0"
    },
    {
        "answer_id": 3476656712,
        "content": "管的宽，不看标题，我还以为这是美军发布的新闻",
        "voteup_count": 12,
        "updated_time": "2024-04-24 09:58:48",
        "question_id": 653529000,
        "user_id": "3d2c8c70660ba63faf1d10c7448cfb85"
    },
    {
        "answer_id": 3476499907,
        "content": "毕竟这游戏非玩不可，当孙子也要玩",
        "voteup_count": 29,
        "updated_time": "2024-04-24 07:37:37",
        "question_id": 653529000,
        "user_id": "540bbb64b76ad810d815462dfe6eb286"
    },
    {
        "answer_id": 3476637379,
        "content": "直接写上不建议玩家玩这个游戏多好",
        "voteup_count": 8,
        "updated_time": "2024-04-24 09:45:02",
        "question_id": 653529000,
        "user_id": "101fff16dfc1829e249b638ce9bced33"
    },
    {
        "answer_id": 3476666079,
        "content": "腾 讯 打 压 python众所周知腾讯是有搞扫盘的，怕不是以后电脑装了python就别想玩腾讯游戏",
        "voteup_count": 6,
        "updated_time": "2024-04-24 10:05:16",
        "question_id": 653529000,
        "user_id": "88f22a18eeb213c5af7228fb64c51e72"
    },
    {
        "answer_id": 3476577427,
        "content": "个人觉得还不够。应该再添加一个Windows，因为Windows本身难道不是最容易触及底层的软件吗？",
        "voteup_count": 25,
        "updated_time": "2024-04-24 09:01:47",
        "question_id": 653529000,
        "user_id": "5bd5027ba7ae9bf103270499c2b57c70"
    },
    {
        "answer_id": 3479175239,
        "content": "我一直没玩腾讯的游戏，有一次好友拉我去玩 CF，我新注册了一个号。我还在等朋友开房间的时候，腾讯说我开挂，把我号封了。。。MDZZ",
        "voteup_count": 8,
        "updated_time": "2024-04-26 11:24:55",
        "question_id": 653529000,
        "user_id": "d3faf15046ba185d5b5e350ade174016"
    },
    {
        "answer_id": 3476854045,
        "content": "感觉有点像当年绿坝的风格不知道怎么开挂是吧, 看, 清单列给你了真的开挂的人:程序员写一个不过分吧, 什么键盘鼠标钩子不是基操? 程序就叫做test.exe你来封个我看看",
        "voteup_count": 20,
        "updated_time": "2024-04-24 12:21:24",
        "question_id": 653529000,
        "user_id": "181bac090311233610c32df7d5c163c4"
    },
    {
        "answer_id": 3476563907,
        "content": "逼事多，还是玩的人太多惯的",
        "voteup_count": 4,
        "updated_time": "2024-04-24 08:51:13",
        "question_id": 653529000,
        "user_id": "64750505f94789a55646c7c5cda8552f"
    },
    {
        "answer_id": 3476395042,
        "content": "我倒是奇怪是什么样的抖M能忍受这么烂的条件去玩一个破游戏。",
        "voteup_count": 40,
        "updated_time": "2024-04-24 00:34:21",
        "question_id": 653529000,
        "user_id": "8b655131beb6523b0ffd5f4833cc6f02"
    },
    {
        "answer_id": 3476417463,
        "content": "乐，只见过玩家找游戏厂商让游戏厂商解决软硬件兼容的，第一次看见游戏厂商让玩家别用软硬件的",
        "voteup_count": 31,
        "updated_time": "2024-04-24 01:25:17",
        "question_id": 653529000,
        "user_id": "f79347173a1fa601677bf452460fcb41"
    },
    {
        "answer_id": 3480390971,
        "content": "我感觉可以预见不久的将来腾讯逼迫用户在wegame和steam上二选一了",
        "voteup_count": 2,
        "updated_time": "2024-04-27 13:39:43",
        "question_id": 653529000,
        "user_id": "c3d5fe7868ce087b30a0e5b2fb53847a"
    },
    {
        "answer_id": 3476133696,
        "content": "cheatengine也算，这玩意儿不是只能改单机？真牛逼",
        "voteup_count": 34,
        "updated_time": "2024-04-23 19:27:27",
        "question_id": 653529000,
        "user_id": "0d2cb43da59591ed15484e67e1011ba3"
    },
    {
        "answer_id": 3476925323,
        "content": "给我的感觉是……正常玩游戏的玩家指不定哪天踩坑就被封号了（鼠标宏、Windbg、Steam Link、NVIDIA Nsight等等，谁也不知道自己正常的软件哪天就变成禁止使用了）。而开挂的玩家……可能反而没事情……（做G第一时间都是先解决反作弊啊……）（当然可能时间长了G没更新会被反作弊抓）或者说，给我的感觉就是像是“我管不动外挂了，所以所有我觉得有可能的，全部封禁完事儿”。我是不太能接受，一个游戏，居然在运行的时候可以扫硬件+扫软件。",
        "voteup_count": 4,
        "updated_time": "2024-04-24 13:31:44",
        "question_id": 653529000,
        "user_id": "3d6eaf40f672b5fea8dbe9502a52e96c"
    },
    {
        "answer_id": 3476981009,
        "content": "“我没能力检测DMA设备，所以老子一刀切。你爱玩不玩，我是你爹”抵制腾讯游戏，拒绝氪金游戏",
        "voteup_count": 14,
        "updated_time": "2024-04-24 14:23:34",
        "question_id": 653529000,
        "user_id": "30dc8b41776764e1400aefab7fcc45f4"
    },
    {
        "answer_id": 3476258055,
        "content": "不准使用虚拟化的前提条件是，他要能知道自己是虚拟化环境，以腾讯的技术水平，还达不到探测当前环境是否是虚拟化环境的技术吧。",
        "voteup_count": 26,
        "updated_time": "2024-04-23 21:51:45",
        "question_id": 653529000,
        "user_id": "b5f98aefb643cffd2d8c150a4ab17b81"
    },
    {
        "answer_id": 3479704605,
        "content": "哈哈哈哈哈哈特色，特色。https://zhuanlan.zhihu.com/p/33723838这让我想起了几年前堡垒之夜港服和国服玩的骚操作，从此以后任何要装腾讯相关启动器的游戏我都敬而远之……",
        "voteup_count": 2,
        "updated_time": "2024-04-26 19:05:58",
        "question_id": 653529000,
        "user_id": "7810af33f5eed8b1b6a6dc0df93f8d6c"
    },
    {
        "answer_id": 3476454369,
        "content": "我建议干脆也别整这么麻烦了找几个硬件厂商，直接整个跟游戏机一样的定制版的系统，再整个应用市场，每个机子再整个机器码到时候把腾讯全家桶都放进去，不买机子的人无法享受腾讯游戏这下哪还有那么多开挂的到时候这么多游戏的安全团队能广进多少啊不然人家随便这边测试个python，另一边启动一下瓦，号封了，自己高价买的国区皮肤用不了了，只能跑去玩玩港服之类的，享受不了国区那美妙的环境，多可惜啊",
        "voteup_count": 23,
        "updated_time": "2024-04-24 05:01:41",
        "question_id": 653529000,
        "user_id": "5b56b9be633a0d33241780043a13a3b8"
    },
    {
        "answer_id": 3474772195,
        "content": "屁事真多，我后台常年挂着todesk和vmware的怎么说？上线就给我封了？",
        "voteup_count": 93,
        "updated_time": "2024-04-22 16:47:51",
        "question_id": 653529000,
        "user_id": "2487271b5fa91496fd09fb47ef112c44"
    },
    {
        "answer_id": 3476956159,
        "content": "不准你这不准你那，自带全家桶和黑名单说封你就封你，花了真金白银的账号，一旦停服、回收账号，你唯一的申诉方法是去南山区腾讯总部天台。我就想知道，哪些人会上赶着当牲口是这世界上游戏太少了吗？",
        "voteup_count": 5,
        "updated_time": "2024-04-24 14:01:17",
        "question_id": 653529000,
        "user_id": "0cf045f2368c3648ca79c2488afa7b8b"
    },
    {
        "answer_id": 3476580147,
        "content": "但凡轻一点的鼠标标上是电竞的都带鼠标宏，腾讯这是想重现3q大战的一角当小丑吗。鼠标都禁了，磁轴键盘呢咋不一起的。是不是最后还得推个对应游戏专用键鼠。",
        "voteup_count": 7,
        "updated_time": "2024-04-24 09:03:56",
        "question_id": 653529000,
        "user_id": "7469a92b729637f0e67a5a69249a3317"
    },
    {
        "answer_id": 3475203842,
        "content": "不开虚拟机vmware也常驻后台，这也管？",
        "voteup_count": 8,
        "updated_time": "2024-04-23 01:11:59",
        "question_id": 653529000,
        "user_id": "36cf2a5f351ede32cabd03bbbf57aa99"
    },
    {
        "answer_id": 3478844270,
        "content": "没啥影响，又不跟pac和valguard冲突一样，有的人不玩游戏还来秀优越。。。",
        "voteup_count": 0,
        "updated_time": "2024-04-26 03:51:44",
        "question_id": 653529000,
        "user_id": "cb166af676d883b91a96a33b1004dbce"
    },
    {
        "answer_id": 3476107993,
        "content": "有啥用呢？挂哥得管，炸鱼的呢？我天天被各种炸鱼的打的头昏脑涨的",
        "voteup_count": 8,
        "updated_time": "2024-04-23 18:54:39",
        "question_id": 653529000,
        "user_id": "05d36ab77c664a2d06b877ce00f271b0"
    },
    {
        "answer_id": 3476462972,
        "content": "腾讯游戏安全中心发布的《无畏契约》禁止和不建议使用的软硬件列表，对玩家使用确实可能产生一定的影响。首先，对于那些习惯使用被禁止或不建议使用的软硬件的玩家来说，他们可能需要重新调整自己的游戏习惯。例如，有些玩家可能依赖特定的硬件或软件来辅助游戏操作，或者利用某些工具来优化游戏体验。现在，他们必须放弃这些工具，并寻找其他合规的方式来享受游戏。其次，这一举措有助于提高游戏的公平性和安全性。禁止黑客工具和具有恶意功能的插件，可以减少作弊和外挂行为，维护游戏的平衡和公正。同时，禁止使用可能影响游戏运行的虚拟化软件，也有助于减少游戏出现错误或崩溃的可能性，提升玩家的游戏体验。然而，对于一些玩家来说，他们可能会对这样的限制感到不满或困惑。他们可能需要花费一定的时间和精力来了解新的规定，并适应没有这些软硬件辅助的游戏环境。腾讯游戏安全中心发布这一列表是为了维护游戏的公平性和安全性，虽然可能会对部分玩家造成一定的影响，但这也是为了保障大多数玩家的利益和游戏体验。同时，这也提醒玩家在选择使用软硬件时要谨慎，确保自己的行为符合游戏的规定和要求。",
        "voteup_count": 4,
        "updated_time": "2024-04-24 05:54:22",
        "question_id": 653529000,
        "user_id": "356335338eddc5e3350581e7a22bbaa9"
    },
    {
        "answer_id": 3476594791,
        "content": "难以置信无法无天",
        "voteup_count": 4,
        "updated_time": "2024-04-24 09:14:47",
        "question_id": 653529000,
        "user_id": "74da1368e9e9d50990b1b08d7d5a5b5b"
    },
    {
        "answer_id": 3476520514,
        "content": "实在没活了，你就把整出这莫名其妙的列表这群人的绩效扣了，发给你们法务，让他们干活",
        "voteup_count": 15,
        "updated_time": "2024-04-24 08:08:59",
        "question_id": 653529000,
        "user_id": "74ae4e7dafc6c515ae4bf098a2053092"
    },
    {
        "answer_id": 3476956724,
        "content": "对普通玩家没有什么影响，因为这只是现在才说，实际上他肯定早就这么做了。这东西更类似于免责条款，意思就是两个不保，这个不保和那个不保，GB不保封，绿玩不保不封。熟悉鹅厂反作弊史的应该都很清楚这一点，当然鹅厂这些年还是有进步的，比如他现在知道跟你说一声，请小心，我可能要误封你了。",
        "voteup_count": 5,
        "updated_time": "2024-04-24 14:01:50",
        "question_id": 653529000,
        "user_id": "1cca66c4c13d3f9187063661f179cfbc"
    },
    {
        "answer_id": 3477295615,
        "content": "这下学会了",
        "voteup_count": 0,
        "updated_time": "2024-04-24 18:45:51",
        "question_id": 653529000,
        "user_id": "bb666400c2e3cbe0a56358771f2b5b7c"
    },
    {
        "answer_id": 3476633636,
        "content": "什么游戏？哦，无畏契约啊，没听说过。给我多少钱让我玩？不给钱，那你送博德之门兑换码吗？什么玩意，不送？那你介绍175大长腿的迪丽热巴给我吗，要不一个月夜店你全买单也行。啥，没有？还要我禁软件？给你脸了是吧。***,*******,**********,********!",
        "voteup_count": 4,
        "updated_time": "2024-04-24 09:42:31",
        "question_id": 653529000,
        "user_id": "5fa8e552d074ae1f42c4ce8fe31ec888"
    },
    {
        "answer_id": 3476466456,
        "content": "我很庆幸没玩鹅厂的游戏",
        "voteup_count": 5,
        "updated_time": "2024-04-24 06:10:42",
        "question_id": 653529000,
        "user_id": "0052fe710b32037a00c7b0902e927e24"
    },
    {
        "answer_id": 3476564809,
        "content": " m服是这样的。都说米在训练忠诚度。可是米玩的都是m 玩剩下的， m的玩家纯度那才叫一个高。",
        "voteup_count": 15,
        "updated_time": "2024-04-24 08:52:25",
        "question_id": 653529000,
        "user_id": "79c83607b6fbbd4d17f24d1930bf410e"
    },
    {
        "answer_id": 3477850523,
        "content": "玩腾讯游戏，蹲赛博监狱。",
        "voteup_count": 1,
        "updated_time": "2024-04-25 09:52:09",
        "question_id": 653529000,
        "user_id": "3bc713a72e72db1194117e65cb330053"
    },
    {
        "answer_id": 3476562023,
        "content": "答案：不玩这游戏就是咯缺它天塌了？",
        "voteup_count": 6,
        "updated_time": "2024-04-24 08:49:43",
        "question_id": 653529000,
        "user_id": "5e867b13e70c459231d1d18dfd0f5a91"
    },
    {
        "answer_id": 3476616480,
        "content": "话分两边。一方面腾讯这么搞确实扯淡。另一方面外服不这么搞不代表外服反作弊系统就好使。这玩儿客观得讲国内作弊代价实在太低了，你要不是主播up主之类得连社死这种算不上惩罚得事都做不到。",
        "voteup_count": 8,
        "updated_time": "2024-04-24 09:30:29",
        "question_id": 653529000,
        "user_id": "28448dbad2a75ab420133af6103834ea"
    },
    {
        "answer_id": 3477255985,
        "content": "WinDbg、ProcessMonitor=黑客工具安装Vmware、Win11自带虚拟化=禁止使用Python、远程桌面=不建议使用？你这什么神仙游戏",
        "voteup_count": 9,
        "updated_time": "2024-04-24 18:10:11",
        "question_id": 653529000,
        "user_id": "2ae9c5e050343ef648ba61bc9e0bbe34"
    },
    {
        "answer_id": 3476765211,
        "content": "Process Monitor都上榜了，没有Visual Studio我不满意捏",
        "voteup_count": 7,
        "updated_time": "2024-04-24 11:11:29",
        "question_id": 653529000,
        "user_id": "b4934222a93899ecf2325c22d908c605"
    },
    {
        "answer_id": 3478839313,
        "content": "谁还不用个罗技鼠标啊！这就不许玩了？",
        "voteup_count": 0,
        "updated_time": "2024-04-26 03:17:32",
        "question_id": 653529000,
        "user_id": "4e8cf4c51cbe1e35011939b338149cdf"
    },
    {
        "answer_id": 3479600057,
        "content": "快进到必须要使用给TX交了认证费的硬件品牌，才能玩他家游戏~",
        "voteup_count": 2,
        "updated_time": "2024-04-26 17:15:12",
        "question_id": 653529000,
        "user_id": "5f11329bf84cc4b29f330b40ed93e5ce"
    },
    {
        "answer_id": 3477150109,
        "content": "Tencent这是要让计算机专业集体破防吗 算了这破国服不玩也罢",
        "voteup_count": 5,
        "updated_time": "2024-04-24 16:39:42",
        "question_id": 653529000,
        "user_id": "ca7503845bcac5fd18d96836323c5b22"
    },
    {
        "answer_id": 3476182230,
        "content": "疑约丁真，鉴定为纯纯的老痰",
        "voteup_count": 5,
        "updated_time": "2024-04-23 20:25:55",
        "question_id": 653529000,
        "user_id": "d75e655b532a7474dbe01d5ce860cbfb"
    },
    {
        "answer_id": 3476512518,
        "content": "不如管管炸鱼，晚上八点以后把把杀三四十个的炸鱼哥能不能似啊",
        "voteup_count": 6,
        "updated_time": "2024-04-24 07:58:09",
        "question_id": 653529000,
        "user_id": "e810295a589191cc760727798f7acb04"
    },
    {
        "answer_id": 3476596833,
        "content": "没关系，我也不建议玩这个游戏。",
        "voteup_count": 2,
        "updated_time": "2024-04-24 09:16:16",
        "question_id": 653529000,
        "user_id": "0cc681a747f6dae6759b5557fad58e3e"
    },
    {
        "answer_id": 3476927280,
        "content": "管的太宽了 傻逼腾讯安全中心 除了扫盘啥都不会",
        "voteup_count": 1,
        "updated_time": "2024-04-24 13:33:36",
        "question_id": 653529000,
        "user_id": "2d15a6f016616bd7662fe1b3efd567b8"
    },
    {
        "answer_id": 3477530772,
        "content": "如果玩个游戏得重买一台落后性能的电脑，我宁愿不玩这个游戏，尤其是，这个游戏还有国际服版本，且国际服没那么多破事的时候。马家游戏铺子是向着倒闭一路狂奔了，这也应该是资本主义下其相应的组织程度等级与规模不匹配现有资本的聚集高度，开始有自分化瓦解的兆头了。",
        "voteup_count": 3,
        "updated_time": "2024-04-24 23:11:45",
        "question_id": 653529000,
        "user_id": "8cd82a50f7fc5d4ab07edd55726ba4d5"
    },
    {
        "answer_id": 3476810078,
        "content": "没啥影响，除非是死忠粉游戏不能玩就不玩了呗，选择那么多，不差这一个去年FIFA24出的时候，因为EA不想花冤枉钱了，是最后一代冠名FIFA的，想买一个做纪念，结果买了下载安装完死活连不上EA那该死的橘子，就退款了，当纪念品也不能真摆着看啊，我一穷鬼你游戏做出来不想让人玩，我也没办法",
        "voteup_count": 1,
        "updated_time": "2024-04-24 11:42:52",
        "question_id": 653529000,
        "user_id": "731f0b958206a6b4da0018d5720f3bb9"
    },
    {
        "answer_id": 3476634915,
        "content": "向日葵这类远控软件也在其中？啥情况？有在使用远控软件的网友都懂，正常来说这玩意都是随着开机启动一直运行在后台的，保证自己有需要控制的时候可以随时控制。不会玩个游戏还得先把这玩意关了吧？那哪天要是忘记关了咋办？",
        "voteup_count": 3,
        "updated_time": "2024-04-24 09:43:23",
        "question_id": 653529000,
        "user_id": "6a7a3e9ad8695e9f98db4291d2784ca5"
    },
    {
        "answer_id": 3476589088,
        "content": "不把玩家当人看",
        "voteup_count": 1,
        "updated_time": "2024-04-24 09:10:39",
        "question_id": 653529000,
        "user_id": "bd3d85197e5d6f1d1fcb23e86a288b1b"
    },
    {
        "answer_id": 3476541072,
        "content": "这个马氏条约是模仿马关条约写的吗？",
        "voteup_count": 3,
        "updated_time": "2024-04-24 08:31:34",
        "question_id": 653529000,
        "user_id": "10cbde106037aea836167841d817e065"
    },
    {
        "answer_id": 3479665371,
        "content": "继续提纯，自有孝子洗地。",
        "voteup_count": 0,
        "updated_time": "2024-04-26 18:18:04",
        "question_id": 653529000,
        "user_id": "43ef9dc16b7514cc8b0a2c166e817728"
    },
    {
        "answer_id": 3482588599,
        "content": "你们还玩腾讯运营的游戏？",
        "voteup_count": 0,
        "updated_time": "2024-04-29 13:55:44",
        "question_id": 653529000,
        "user_id": "51633f2a4c02cb45a1ec60e37f40de47"
    },
    {
        "answer_id": 3476568682,
        "content": "提纯，浓缩，结晶",
        "voteup_count": 2,
        "updated_time": "2024-04-24 08:54:57",
        "question_id": 653529000,
        "user_id": "d4ab801245deff2eeb63a2d14e61353b"
    },
    {
        "answer_id": 3479010818,
        "content": "不玩这游戏直接没有影响。又不是什么牛逼到飞起的玩意非玩不可。",
        "voteup_count": 1,
        "updated_time": "2024-04-26 09:27:26",
        "question_id": 653529000,
        "user_id": "c89078938b0a6b58e131d1ef1cb6b0ba"
    },
    {
        "answer_id": 3479261856,
        "content": "有一种赛博贞操带的美感   我这种搞开发的，电脑上hyper-v wsl ce olly ida用的飞起，正好戒网瘾了哦原来我没网瘾啊，我一般都玩单机",
        "voteup_count": 1,
        "updated_time": "2024-04-26 12:38:29",
        "question_id": 653529000,
        "user_id": "50f70fca088a2bd01d05cc6140a83ddc"
    },
    {
        "answer_id": 3479655588,
        "content": "就这样还要跪舔这游戏，gui男这么抽象的吗？还是说这游戏非玩儿不可？",
        "voteup_count": 1,
        "updated_time": "2024-04-26 18:06:42",
        "question_id": 653529000,
        "user_id": "8d21f7e654091286dd237c7d7e23f5fb"
    },
    {
        "answer_id": 3476837414,
        "content": "这波我站360，这破游戏监控我电脑是吧？非玩不可吗！",
        "voteup_count": 1,
        "updated_time": "2024-04-24 12:04:48",
        "question_id": 653529000,
        "user_id": "f0392f614171527f6c17dc39bc5cc739"
    },
    {
        "answer_id": 3477016949,
        "content": "行了，我这种天天按键精灵ce向日葵renderdoc的可以不用玩了",
        "voteup_count": 1,
        "updated_time": "2024-04-24 14:53:46",
        "question_id": 653529000,
        "user_id": "34da7182b2ee18ba53482d3f7b912a03"
    },
    {
        "answer_id": 3476644918,
        "content": "牛逼啊,幸亏我不玩,没这烦恼.",
        "voteup_count": 1,
        "updated_time": "2024-04-24 09:50:25",
        "question_id": 653529000,
        "user_id": "2964963a7002f1723f1fef53df9b1cef"
    },
    {
        "answer_id": 3476873402,
        "content": "幸好我不玩马服游戏",
        "voteup_count": 0,
        "updated_time": "2024-04-24 12:39:19",
        "question_id": 653529000,
        "user_id": "8eff048379de7b581e85dd021bcac285"
    },
    {
        "answer_id": 3480888588,
        "content": "3Q大战明文版这下不得不下下来研究了",
        "voteup_count": 0,
        "updated_time": "2024-04-27 23:42:42",
        "question_id": 653529000,
        "user_id": "088b55167be20d3e25817b9a523dc78e"
    },
    {
        "answer_id": 3478261237,
        "content": "腾讯游戏，狗都不玩",
        "voteup_count": 0,
        "updated_time": "2024-04-25 15:16:47",
        "question_id": 653529000,
        "user_id": "5a78e625de71c2fd990b1c733e0656fd"
    },
    {
        "answer_id": 3476693382,
        "content": "2024年了还以为是十年前，高高在上的模样真恶心",
        "voteup_count": 0,
        "updated_time": "2024-04-24 10:24:18",
        "question_id": 653529000,
        "user_id": "11c87559d6dea8e6ba3bf9a24d37993d"
    },
    {
        "answer_id": 3476464766,
        "content": "是该管，要不这游戏就被挂霍霍黄了，你也可以选择不玩，这游戏现在的情况就是超凡局以上五局四把挂真不是开玩笑，这游戏明明玩家增长没几个月，现在却已经到了不禁挂死路一条的程度，挂钩泛滥出了名的，也只能怪国人玩个比竞技游戏也喜欢当挂钩，我也不知道为啥国服玩家就这么喜欢开挂，丢脸丢到全世界。另外说归说，执行力度如何还是有待观察，就因为技术不够，所以才用这种地毯式轰炸的手段，现在的外挂产业链已经狂上天了，DMA，AI齐上阵，根本检测不出来，如果再加点演技或者时开时不开根本封不了，巨大的利润搞得PUBG，Apex这些没国服的都全都是开挂的国人。虽然我觉得最后还是管不住就是了，除非人脸识别，不过换言之，就这种程度要是还禁不住外挂那就更乐了",
        "voteup_count": 3,
        "updated_time": "2024-04-24 06:13:14",
        "question_id": 653529000,
        "user_id": "175e37bc98722530c26658b78cc60d5b"
    },
    {
        "answer_id": 3476614612,
        "content": "你们搁这笑忠诚度高，我哭我号上各式各样的枪皮谁不是顶着马服10:1充的钱，那能咋办呢更何况，知乎er一个个特战英豪大神，然后和你长期组排的傻子有几个会开加速器的? 人都不知道啥是驱动啥是向日葵啥是宏，就知道xx月xx号，腾讯fps大作无畏契约登录国服，现在下载wegame一键安装注册学生信息更能畅想免费特工和皮肤，能咋办呢?这就是我们藤子啊，真是反作作又弊弊。",
        "voteup_count": 9,
        "updated_time": "2024-04-24 09:29:05",
        "question_id": 653529000,
        "user_id": "3bf32753af3b859f6395bab3aaf6af4b"
    },
    {
        "answer_id": 3479685341,
        "content": "所以呢？禁的都是工作室和挂哥，和你普通玩家有坤关系。",
        "voteup_count": 0,
        "updated_time": "2024-04-26 18:41:42",
        "question_id": 653529000,
        "user_id": "da52b4d61f6c0ff7a1fa869bee92f172"
    },
    {
        "answer_id": 3475551164,
        "content": "这要是给我号封了，我就笑了，向日葵开机自启的（经常需要用），显卡英伟达的，鼠标罗技自带宏只是我没有用而已，封了又不退款，纯送钱吗，再说了我一个白银仔因为这个被封，不是搞笑吗",
        "voteup_count": 7,
        "updated_time": "2024-04-23 11:03:37",
        "question_id": 653529000,
        "user_id": "61372ba1c18e58d0ed3a2fe32a829960"
    },
    {
        "answer_id": 3477032757,
        "content": "☝️ 哎！我有一招你直接推出定制主机、显示器以及全套外设系统也用定制的玩家要购买你的硬件和软件才能玩上这样不是既能赚一波又能有效减少作弊现象？",
        "voteup_count": 7,
        "updated_time": "2024-04-24 15:07:03",
        "question_id": 653529000,
        "user_id": "d5484c3e9a97699f6d3716e61a4d2513"
    },
    {
        "answer_id": 3476608558,
        "content": "追求竞技的玩家如果对反作弊有意见，那只会是嫌弃反作弊力度不够大，特别是射击游戏；娱乐玩家也不适合玩鹅厂代理的那两款拳头游戏，也就是lol和瓦，lol很多人都骂频繁更新导致不会玩游戏，但事实上每个版本都能玩个几十盘排位的人只会盼着更新，天天守着官网/小绿毛提前看更新内容；但是类似的问题永远都是云玩家+娱乐玩家的声量远远大于竞技玩家，甚至让这些云哥/半云哥觉得自己才是代表玩家需求的一方；",
        "voteup_count": 6,
        "updated_time": "2024-04-24 09:24:30",
        "question_id": 653529000,
        "user_id": "702d76bd82f5b82c6cc3bcd0d770a498"
    },
    {
        "answer_id": 3476510451,
        "content": "不如禁用windows把自己做成操作系统",
        "voteup_count": 7,
        "updated_time": "2024-04-24 07:55:01",
        "question_id": 653529000,
        "user_id": "a433873bcd9a987f911648ef6818a1b8"
    },
    {
        "answer_id": 3476508362,
        "content": "腾讯游戏玩家忍耐力令人钦佩",
        "voteup_count": 2,
        "updated_time": "2024-04-24 07:51:37",
        "question_id": 653529000,
        "user_id": "457edfc42272f1b9b56e3806aef1c94d"
    },
    {
        "answer_id": 3477144114,
        "content": "你得有多受虐狂才会玩腾讯游戏？我早就逃离一切国服游戏了。现在就看这些厂翻云覆雨好不自在",
        "voteup_count": 4,
        "updated_time": "2024-04-24 16:35:04",
        "question_id": 653529000,
        "user_id": "e01fb9432a24860b641c50a5a3c8a380"
    },
    {
        "answer_id": 3476671552,
        "content": "讲个跟题目无关的热知识：n年前的时候，你的电脑要是启动过tp系统，golang编译出来的pe文件格式会出问题，不知道现在修复没有。",
        "voteup_count": 4,
        "updated_time": "2024-04-24 10:08:57",
        "question_id": 653529000,
        "user_id": "c8302e5a4cbb0d761825cb3dbd96763c"
    },
    {
        "answer_id": 3476762416,
        "content": "根据我多年被坑的经验，玩游戏的唯一建议就是不要玩服务器在国内的任何游戏。因为游戏丰富程度不是一个档次、游戏和谐程度不是一个档次、服务器水平不是一个档次、游戏内购价格不是一个档次。",
        "voteup_count": 3,
        "updated_time": "2024-04-24 11:09:43",
        "question_id": 653529000,
        "user_id": "f61372703ecf3e3fe3273cfe2125337a"
    },
    {
        "answer_id": 3476739940,
        "content": "不是很懂为什么这么多人玩这个b马服 充值又贵挂又多还这么多条条框框 感觉玩马服的多多少少带点M属性",
        "voteup_count": 3,
        "updated_time": "2024-04-24 10:55:33",
        "question_id": 653529000,
        "user_id": "bdfdcaf07cd655ff996001ec89c0dc9f"
    },
    {
        "answer_id": 3476587688,
        "content": "为啥反应这么不好？我只看到了腾讯游戏宁愿顶着骂名也要把外挂封禁做到底的决心啊！这有什么不好的，为什么国外这样做的少？还不是因为国外开的人少，国内开的人多自然要用更严厉的手段去禁止啊！",
        "voteup_count": 11,
        "updated_time": "2024-04-24 09:09:35",
        "question_id": 653529000,
        "user_id": "9a38dda9c01a58c84c9c22c49aac0ad5"
    },
    {
        "answer_id": 3476984019,
        "content": "看到清一色骂的，作为实际玩家来说我是挺赞成的。现在的fps游戏外挂多的难以想象，手段也非常之多。正常小开+演是非常难看出来的。当你一直被对面抓timing 真的难受 你不知道对面是挂还是运气好。所以作为实际玩家我是非常愿意牺牲部分权力支持厂商全力针对外挂的。因为感受过apex司马厂商不作为，才知道珍惜愿意全力打击外挂的游戏多么难得。",
        "voteup_count": 3,
        "updated_time": "2024-04-24 14:26:04",
        "question_id": 653529000,
        "user_id": "43ccf04679b25d3fe7562a5db3692060"
    },
    {
        "answer_id": 3481472222,
        "content": "想到之前玩LOL每局固定时间就会TP把我t出去，找了很久解决方案，结果最后是在TP吧很深的角落找到有人说你是不是下了render doc。我然后立马卸载，玩了几把都不掉。然后我不玩LOL了（lol）。————————而且反映了贴吧才是真正存在金子的地方（暴论）（笑）",
        "voteup_count": 2,
        "updated_time": "2024-04-28 14:05:19",
        "question_id": 653529000,
        "user_id": "5904e5a23ddcc95705f54eef1b4aca91"
    },
    {
        "answer_id": 3481203950,
        "content": "python不让用，这是筛选谁呢？是不是java jvm过两天也要禁止了？",
        "voteup_count": 2,
        "updated_time": "2024-04-28 10:17:31",
        "question_id": 653529000,
        "user_id": "57070afe33411feca7082a0589b4df1d"
    },
    {
        "answer_id": 3478505875,
        "content": "谁能从法律角度帮我解读一下啥叫破坏计算机系统信息罪？",
        "voteup_count": 2,
        "updated_time": "2024-04-25 18:47:22",
        "question_id": 653529000,
        "user_id": "89850ae9b33c08f0b4de6f5e33c4b2f1"
    },
    {
        "answer_id": 3478352446,
        "content": "我感觉腾讯办比赛办High了。因为这东西我怎么看都是像从职业联赛的参赛要求里节选出来的，对于职业联赛的选手这么要求完全无可厚非。但用职业联赛要求选手的标准去要求一般玩家……？",
        "voteup_count": 2,
        "updated_time": "2024-04-25 16:26:38",
        "question_id": 653529000,
        "user_id": "7d92a88271d55715d5f061fdadd9a2d0"
    },
    {
        "answer_id": 3477446964,
        "content": "EAAC不让我用procmon也就是检测到它运行过之后拒绝启动游戏罢了，该骂骂但重启一下电脑就开始玩这光荣榜上的软件我至少有四成你玩腾讯游戏吗？反正我不玩",
        "voteup_count": 2,
        "updated_time": "2024-04-24 21:40:24",
        "question_id": 653529000,
        "user_id": "79198d19c927e8bdddbee4608480ada7"
    },
    {
        "answer_id": 3477037346,
        "content": "有没有可能这个是免责条款以后腾讯封你号 就说你有以上行为 封你活该",
        "voteup_count": 2,
        "updated_time": "2024-04-24 15:10:39",
        "question_id": 653529000,
        "user_id": "9091cfd061534747e9c43f5ce38ed0f1"
    },
    {
        "answer_id": 3476738771,
        "content": "这破游戏，不值得我这么费心尽力，爱谁谁原神启动！",
        "voteup_count": 2,
        "updated_time": "2024-04-24 10:54:47",
        "question_id": 653529000,
        "user_id": "157701d441cd137f8938abbc490d6e15"
    },
    {
        "answer_id": 3476738427,
        "content": "惊呆了，还好这游戏我不玩，计算机是个综合设备，不单单是个游戏机，尤其很多软件我工作是必须要用的。建议游戏反外挂反魔怔的安全部门不要太霸道，搞些自以为是的村规，说到底这么做你就真能杜绝外挂了吗？不过是给普通玩家制造麻烦罢了。",
        "voteup_count": 2,
        "updated_time": "2024-04-24 10:54:34",
        "question_id": 653529000,
        "user_id": "75fb16808f346529f8168a14ad94394e"
    },
    {
        "answer_id": 3476686363,
        "content": "真正的挂狗是一个抓不到，欺负顺民是手到擒来。",
        "voteup_count": 2,
        "updated_time": "2024-04-24 10:19:22",
        "question_id": 653529000,
        "user_id": "60cab3acecce7c655b154debd9118976"
    },
    {
        "answer_id": 3476678374,
        "content": "这个估计是无畏契约的另类推广吧？就这个消息我才知道还有这个游戏，要说禁止外挂的话，lol，cf，和平精英咋不也给发个这样的公告？好了，个人黑名单+1。",
        "voteup_count": 3,
        "updated_time": "2024-04-24 10:13:36",
        "question_id": 653529000,
        "user_id": "3a57ac8f521dc105c087458ca357d3aa"
    },
    {
        "answer_id": 3476605748,
        "content": "大家都不玩就行了，一个破游戏就想控制别人。谁给你那么大的勇气？",
        "voteup_count": 2,
        "updated_time": "2024-04-24 09:22:32",
        "question_id": 653529000,
        "user_id": "0585b847af1349a5fd333be61a453127"
    },
    {
        "answer_id": 3476603946,
        "content": "这么多我记不住 我选择不玩",
        "voteup_count": 2,
        "updated_time": "2024-04-24 09:21:10",
        "question_id": 653529000,
        "user_id": "05e7bc95683e5441840a68e7d63115e3"
    },
    {
        "answer_id": 3476591984,
        "content": "这游戏，能赚钱？非玩不可？没有其他fps了？",
        "voteup_count": 2,
        "updated_time": "2024-04-24 09:12:42",
        "question_id": 653529000,
        "user_id": "b99f6ed694bd2661b2047e82710237ef"
    },
    {
        "answer_id": 3476571066,
        "content": "腾讯玩家，游戏界的江西老哥",
        "voteup_count": 2,
        "updated_time": "2024-04-24 08:56:55",
        "question_id": 653529000,
        "user_id": "a236013f1fb13026db554962da398fb6"
    },
    {
        "answer_id": 3476570365,
        "content": "现在流行提纯.建议加快速度.把装了其他游戏的全封了.你的电脑只能有我鹅厂的游戏,否则就是叛徒,封封封!",
        "voteup_count": 2,
        "updated_time": "2024-04-24 08:56:23",
        "question_id": 653529000,
        "user_id": "c79f9af2421da9b528fa2576ed9ae640"
    },
    {
        "answer_id": 3476493629,
        "content": "你们记得杨笠是怎么凉的吗？就是因为只要她敢代言一款男性产品这个产品的淘宝、抖音等一系列直播间会遭到如山如海一般的网络袭击逼得这帮敢于挑衅男性用户的厂商纷纷发声明割席——问题来了，为何英雄联盟、dnf等游戏玩家经常被马家恶心？因为某些人没种你活该",
        "voteup_count": 2,
        "updated_time": "2024-04-24 07:25:28",
        "question_id": 653529000,
        "user_id": "21d17cd2bf45d255a8db4bed8bbfc51b"
    },
    {
        "answer_id": 3476464271,
        "content": "腾讯有本事自己搞个游戏机和任天堂索尼微软竞争，你自己搞的游戏机就是要求用户必须吃屎也管不着。",
        "voteup_count": 2,
        "updated_time": "2024-04-24 06:00:54",
        "question_id": 653529000,
        "user_id": "e38dbdabef3271d8d555364c3fe4c508"
    },
    {
        "answer_id": 3476833608,
        "content": "这对玩家使用造成什么影响？对“真玩家”来说，大概率是没有影响。虽然在知乎大家都觉得腾讯恶心人，这也不允许那也不允许，纯纯恶心人，国服瓦要凉，谁玩谁龟但是从绝大多数普通玩家的角度，这有个锤子的影响，列出来的这些软硬件，平时也不用呀。玩游戏就好好玩呗，后台开这开那的干什么玩意。真有哥们说，我日常后台挂着XXX呢，相信我，这样的是少数。绝大多数人，只是简简单单玩游戏的“普通人”。出来反对的人的意见，毫无意义。即使明天腾讯出来说：玩任何腾讯游戏的时候不能使用插入式猫尾巴，我们有黑科技检测到就永封。依然可能会有人反对，因为说不定真的有人在游戏的时候一定要使用插入式猫尾巴。这无理吗？无理。但是对普通玩家来说，这有影响吗，没有。如果真有正义感的人站出来说，虽然我打游戏时不用插入式猫尾巴，但是我誓死捍卫别人打游戏时使用插入式猫尾巴的权利。那我只能说，先生大义。",
        "voteup_count": 5,
        "updated_time": "2024-04-24 12:15:30",
        "question_id": 653529000,
        "user_id": "a6af065cbd77735a60a69a91427f50b9"
    },
    {
        "answer_id": 3476598749,
        "content": "虽然我不玩，但是我赞同。不理解这个规则的可以不玩这个游戏。反而这个规则会让游戏环境好很多，对待挂√，宁可错杀一千也不放过一个",
        "voteup_count": 3,
        "updated_time": "2024-04-24 09:17:35",
        "question_id": 653529000,
        "user_id": "619d170e0cc16b4593de7b86763b0534"
    },
    {
        "answer_id": 3479677472,
        "content": "这根本就没有切中要害呀。开挂打游戏的无非就是赚钱的，普通玩家开挂打游戏对游戏影响真不大，如果没有金钱收入的话，开挂是收钱的。对于主播你可以做一些硬件上的设置，代打或者陪玩，你直接限制账号登陆地或者个人注册数量不就完事了。",
        "voteup_count": 1,
        "updated_time": "2024-04-26 18:32:25",
        "question_id": 653529000,
        "user_id": "07d3d2f721babf89ee9fc247fcd9a14d"
    },
    {
        "answer_id": 3477341475,
        "content": "建议检查一下，有没有米哈游全家桶。检测……loading……原神，启动！",
        "voteup_count": 1,
        "updated_time": "2024-04-24 19:38:30",
        "question_id": 653529000,
        "user_id": "5ee123d4cb3a1892ff03f7a2f31c1fa6"
    },
    {
        "answer_id": 3477158677,
        "content": "就很好奇有没有大佬真用这些软件拿下过它服务器(°∀°)",
        "voteup_count": 1,
        "updated_time": "2024-04-24 16:46:07",
        "question_id": 653529000,
        "user_id": "014aabff7b249a6cf862bc3868ce0a27"
    },
    {
        "answer_id": 3477121744,
        "content": "打游戏的时候不能开远程？那你对象说她不会启动游戏怎么办？",
        "voteup_count": 1,
        "updated_time": "2024-04-24 16:17:36",
        "question_id": 653529000,
        "user_id": "515bf758f2a1f3ef73f608a677399dc5"
    },
    {
        "answer_id": 3477041953,
        "content": "这个鬼游戏曾经有段时间一直说我使用违规外设封号1小时，后来又不封了，从始至终我都用的蝰蛇V2X，连侧键都没用过捏马的",
        "voteup_count": 1,
        "updated_time": "2024-04-24 15:14:21",
        "question_id": 653529000,
        "user_id": "5605854afd7d0211028c970e6c7578bf"
    },
    {
        "answer_id": 3476964245,
        "content": "好几年前我就因为用雨滴桌面读取cpu占用率的插件被LOL封过一周，现在虚拟化、远程桌面这类的工具这么普遍，以及主播使用的obs、采集卡等设备普及，游戏进程与外挂的隔离方法越来越简单，对于反作弊来说确实面临巨大的挑战，但采取禁止用户使用流行软件的方法纯粹是技术部门甩锅的体现，在这之前怎么不禁止？还不是因为游戏营收不佳，问玩家意见，首当其冲的就是外挂泛滥，尤其是fps、moba等竞技类游戏，不想办法解决问题，就一甩了之。就像当初LOL玩家反映演员代练泛滥，运营想出来的是隐藏战绩不让玩家查询，你就不知道谁是代练谁是演员了；玩家反映游戏环境差，挂机喷人者众，运营想出来的是关闭所有人频道，加一堆莫名其妙的屏蔽词，甚至疑似使用机器学习训练增加屏蔽词库，以至于打出河南两个字，直接被封号。最后的结果呢，全是反作用，加速玩家流失，一区排位两分钟，郊区排位五分钟，现在合区都救不回来。今时不比往日，人人必有手机，而人人不必有PC，时时摸得到手机，而无人时时摸得到PC，因此现在端游的门槛本就比手游高，再搞出这种限制软件使用，是让玩家们专门配一台纯净系统，只装腾讯全家桶的主机来打游戏吗？毫无疑问，对于打击外挂改善游戏环境来留住玩家的出发点，绝对又是反作用。这一系列技术和运营的决定的做出，充分暴露了腾讯端游管理层的无能，脚痛砍脚，头痛砍头，无效KPI的制定，倒逼普通员工只顾眼前领导的要求，等到年底又把营收下降的责任归到游戏市场不景气，然后再裁一批员工，来年再想新的幺蛾子害人害己。",
        "voteup_count": 1,
        "updated_time": "2024-04-24 14:09:02",
        "question_id": 653529000,
        "user_id": "9d24c2c4bb4ac9c7830ee6c41af5b792"
    },
    {
        "answer_id": 3476822846,
        "content": "腾讯不建议我使用这些软件，那我只能不建议游玩马服无畏契约了",
        "voteup_count": 2,
        "updated_time": "2024-04-24 11:52:34",
        "question_id": 653529000,
        "user_id": "3a9e3f9cc4910de0ec26a66492c0b67b"
    },
    {
        "answer_id": 3476598987,
        "content": "玩个游戏这么多要求的吗？封外挂也不是这么个封法吧",
        "voteup_count": 1,
        "updated_time": "2024-04-24 09:17:46",
        "question_id": 653529000,
        "user_id": "300a54e6abefc6cfa8152270e2c8e6d5"
    },
    {
        "answer_id": 3476582430,
        "content": "有两种可能：1、这是一篇科普文章，在此之前我只认识CE，现在知道原来还有那么多软件。2、核心技术人员离职了，新的游戏程序无法应对各类软件的运行兼容，可能随时崩溃，在崩溃前先发一波通知，这样不能够正常游戏时，玩家就会怀疑是系统检测到外挂，而不会想到就是程序太垃圾，不兼容崩溃了。",
        "voteup_count": 2,
        "updated_time": "2024-04-24 09:05:42",
        "question_id": 653529000,
        "user_id": "b8a3d34a07111deb6d4595a97813de03"
    },
    {
        "answer_id": 3476573464,
        "content": "无畏契约 有人玩啊？我以为凉了呢。 这游戏跟OW有什么区别",
        "voteup_count": 1,
        "updated_time": "2024-04-24 08:58:50",
        "question_id": 653529000,
        "user_id": "d9e119f738866160fdcb3739f716154d"
    },
    {
        "answer_id": 3476490377,
        "content": "这列表有意思，在科普啥？",
        "voteup_count": 1,
        "updated_time": "2024-04-24 07:18:33",
        "question_id": 653529000,
        "user_id": "7ac919f02a21d46156c815a1eefc666a"
    },
    {
        "answer_id": 3476473103,
        "content": "脸呢？不要了？哦哦，原来他没有。",
        "voteup_count": 1,
        "updated_time": "2024-04-24 06:34:34",
        "question_id": 653529000,
        "user_id": "7f457c951215d0887bcbd15411a652cb"
    },
    {
        "answer_id": 3476738120,
        "content": "知乎也这么多外挂党吗？玩竞技游戏防外挂多重要",
        "voteup_count": 2,
        "updated_time": "2024-04-24 10:54:24",
        "question_id": 653529000,
        "user_id": "84666d08bfb0731507fc3ba9dba107cf"
    },
    {
        "answer_id": 3479149148,
        "content": "都在喷，我只能说你们大概率不喜欢玩这款游戏，就算玩过也只是玩玩。如果真的能把大部分挂封掉的话，我挺支持的，一是因为我电脑上也没有那些东西，二是开挂的确实恶心人。",
        "voteup_count": 1,
        "updated_time": "2024-04-26 11:07:24",
        "question_id": 653529000,
        "user_id": "7a06fb220ef64b5821efcedd3cc343cf"
    },
    {
        "answer_id": 3476676959,
        "content": "尽管去年开始我发誓不再相信白人开的暴雪公司，因为那里充满了欺骗虚伪残害PUA玩家的东西，但面对鹅厂我还是认为暴雪还是值得信任的",
        "voteup_count": 1,
        "updated_time": "2024-04-24 10:12:31",
        "question_id": 653529000,
        "user_id": "52a2a232bfd192bc604c53b09370103c"
    },
    {
        "answer_id": 3480784356,
        "content": "众所周知，腾讯游戏不充钱，不开挂不开脚本纯手动玩都概率封号10年；充一点钱，脚本就不封；重氪的号，开了挂被封号找超核秒解。",
        "voteup_count": 0,
        "updated_time": "2024-04-27 21:43:07",
        "question_id": 653529000,
        "user_id": "4f85597453cac4fb0d7a569593d440ac"
    },
    {
        "answer_id": 3480270889,
        "content": "要不腾讯自己做个主机吧，",
        "voteup_count": 0,
        "updated_time": "2024-04-27 11:21:25",
        "question_id": 653529000,
        "user_id": "e37182c5b18a2eb6bc5d85c769badcc6"
    },
    {
        "answer_id": 3479232762,
        "content": "融合器?指的是投影机边缘融合吗",
        "voteup_count": 0,
        "updated_time": "2024-04-26 12:08:44",
        "question_id": 653529000,
        "user_id": "9904919ce11256276ebb8c603172e6b9"
    },
    {
        "answer_id": 3478158501,
        "content": "猜猜为什么那么多人又回去玩CS2了？",
        "voteup_count": 1,
        "updated_time": "2024-04-25 13:50:58",
        "question_id": 653529000,
        "user_id": "13428975d7faa56334a87a7bc734e06a"
    },
    {
        "answer_id": 3477378215,
        "content": "管的真宽 ",
        "voteup_count": 0,
        "updated_time": "2024-04-24 20:20:55",
        "question_id": 653529000,
        "user_id": "b7c1566105a26860c7d5c27c10ebbde9"
    },
    {
        "answer_id": 3476906689,
        "content": "腾讯 都不玩",
        "voteup_count": 0,
        "updated_time": "2024-04-24 13:12:17",
        "question_id": 653529000,
        "user_id": "478777294e74b7975d4900bd33e1c87b"
    },
    {
        "answer_id": 3476895844,
        "content": "倒反天罡",
        "voteup_count": 0,
        "updated_time": "2024-04-24 13:01:50",
        "question_id": 653529000,
        "user_id": "07cbd60627ee3a0c9337672cffbbad6c"
    },
    {
        "answer_id": 3476744453,
        "content": "虚拟化都不让用也太……",
        "voteup_count": 0,
        "updated_time": "2024-04-24 10:58:42",
        "question_id": 653529000,
        "user_id": "2e6c7a0cf8c76dacb99c04edc58bacac"
    },
    {
        "answer_id": 3476686375,
        "content": "没什么影响我玩别的去呗",
        "voteup_count": 0,
        "updated_time": "2024-04-24 10:19:23",
        "question_id": 653529000,
        "user_id": "a849dca993058ce5491514e1380b14a2"
    },
    {
        "answer_id": 3476661903,
        "content": "开始提纯玩家喽",
        "voteup_count": 0,
        "updated_time": "2024-04-24 10:02:20",
        "question_id": 653529000,
        "user_id": "9c41f4f6205b205232c2adaab818150a"
    },
    {
        "answer_id": 3477547640,
        "content": "腾讯的这一行为，长远来看，是为了优化游戏环境，保护大多数玩家的利益。然而，在短期内，玩家可能需要适应这一变化，尤其是那些习惯了某些被禁止或不建议使用的软硬件的玩家。对合规玩家的正面影响公平性提升：禁止使用作弊工具和硬件，使得游戏环境更加公平，提升了玩家的游戏体验。安全增强：减少了因作弊导致的账号封禁风险，保护了合规玩家的权益。对习惯使用被禁软硬件的玩家的影响适应期：习惯了使用某些被禁软硬件的玩家可能需要一个适应期来改变他们的游戏习惯。游戏体验变化：部分玩家可能会感觉到游戏体验的变化，尤其是那些依赖特定硬件或软件来提升操作便利性的玩家。对游戏社区的长期影响社区氛围改善：打击作弊行为有助于营造一个积极的游戏社区氛围，促进玩家之间的良性互动。玩家信任增强：腾讯的这一举措有助于增强玩家对游戏公平性和官方维护正义的信任。经济影响成本考虑：对于已经购买了被禁止使用的硬件的玩家来说，这可能意味着一定的经济损失。消费决策调整：未来玩家在购买游戏相关硬件和软件时，可能会更加谨慎，考虑其是否符合游戏官方的规定。利大于弊的长期效应尽管腾讯游戏安全中心发布的禁止和不建议使用的软硬件列表可能会给部分玩家带来短期的不便，但从长远来看，这一举措对整个游戏生态和大多数玩家来说是有益的。它有助于维护游戏的公平性，打击作弊行为，提升玩家的整体游戏体验。玩家应当理解并支持这一政策，适应新的游戏环境，共同营造一个公正、健康的游戏空间。同时，腾讯和游戏开发者也应继续监控和更新这一列表，确保其与游戏发展保持同步，并适时为玩家提供必要的指导和支持。",
        "voteup_count": 1,
        "updated_time": "2024-04-24 23:32:00",
        "question_id": 653529000,
        "user_id": "ad90a4cf02c932c6ff4bb5e63f070a09"
    },
    {
        "answer_id": 3476638041,
        "content": "一看就事很多的样子好麻烦",
        "voteup_count": 0,
        "updated_time": "2024-04-24 09:45:28",
        "question_id": 653529000,
        "user_id": "4882224c895260fecaa83f6a596cd4c7"
    },
    {
        "answer_id": 3476602103,
        "content": "这逼游戏已经三个月没玩了，不知道为什么，我一旦杀人多一点就说我作弊，给强退了，一查说我账号异地登录？我真是日了狗！",
        "voteup_count": 0,
        "updated_time": "2024-04-24 09:19:56",
        "question_id": 653529000,
        "user_id": "b9fff6a382aca4aab91ccca5428fc762"
    },
    {
        "answer_id": 3476587202,
        "content": "感谢题主，我这就去学",
        "voteup_count": 0,
        "updated_time": "2024-04-24 09:09:15",
        "question_id": 653529000,
        "user_id": "170bec94576748dbdd3493df0cbff6be"
    },
    {
        "answer_id": 3476561988,
        "content": "没办法，实在没有游戏玩了，随便他吧",
        "voteup_count": 0,
        "updated_time": "2024-04-24 08:49:41",
        "question_id": 653529000,
        "user_id": "5c6db98f92904d6c7af7e73b11dc0ebf"
    },
    {
        "answer_id": 3476492343,
        "content": "终于有慈禧向全世界开战的感觉了",
        "voteup_count": 1,
        "updated_time": "2024-04-24 07:22:58",
        "question_id": 653529000,
        "user_id": "12af42069365911f2e46379b26a036a0"
    },
    {
        "answer_id": 3476466974,
        "content": "太高贵我不想玩了，但是能不能退款？毕竟是你让我做的选择",
        "voteup_count": 0,
        "updated_time": "2024-04-24 06:12:46",
        "question_id": 653529000,
        "user_id": "aaf9dd7626a7f56be0020435db1b9f23"
    },
    {
        "answer_id": 3476454677,
        "content": "不愧是你，幸好不玩马服",
        "voteup_count": 0,
        "updated_time": "2024-04-24 05:04:03",
        "question_id": 653529000,
        "user_id": "3369df047b546e6a2850883f34ba25c6"
    },
    {
        "answer_id": 3476637073,
        "content": "腾讯游戏安全中心发布软硬件列表，禁止和不建议使用《 无畏契约 》，这对玩家使用造成什么响？",
        "voteup_count": 0,
        "updated_time": "2024-04-24 09:44:50",
        "question_id": 653529000,
        "user_id": "2252bce6c45bcca57ecdd26607d1fce2"
    },
    {
        "answer_id": 3477479443,
        "content": "PC游戏的命，主机游戏的病",
        "voteup_count": 0,
        "updated_time": "2024-04-24 22:15:13",
        "question_id": 653529000,
        "user_id": "25c0815572d5985a0e9194428fbf7a7d"
    },
    {
        "answer_id": 3476506247,
        "content": "不知道的还以为大家求着腾讯，让玩家能玩到无畏契约。一个CSGO换皮的抄袭之作而已，又不是没有其他游戏，比如玩正版的CSGO。",
        "voteup_count": 0,
        "updated_time": "2024-04-24 07:48:20",
        "question_id": 653529000,
        "user_id": "466a1fae2a1e40c4eea85c38ab39e74d"
    }
]